{"v":"5.9.0","fr":29.9700012207031,"ip":0,"op":148.000006028164,"w":902,"h":705,"nm":"\ncircle/250105_businessmodel 2","ddd":0,"assets":[{"id":"image_0","w":1316,"h":505,"u":"images/","p":"img_0.png","e":0}],"fonts":{"list":[{"fName":"Outfit-Bold","fFamily":"Outfit","fStyle":"Bold","ascent":72.5997924804688},{"fName":"NotoSansJP-Regular","fFamily":"Noto Sans JP","fStyle":"Regular","ascent":79.5989990234375},{"fName":"NotoSansJP-Bold","fFamily":"Noto Sans JP","fStyle":"Bold","ascent":79.7988891601562}]},"layers":[{"ddd":0,"ind":1,"ty":4,"nm":"border1","sr":1,"ks":{"o":{"a":0,"k":100,"ix":11},"r":{"a":0,"k":0,"ix":10},"p":{"a":0,"k":[309,352.5,0],"ix":2,"l":2},"a":{"a":0,"k":[67.5,67.5,0],"ix":1,"l":2},"s":{"a":0,"k":[100,100,100],"ix":6,"l":2}},"ao":0,"shapes":[{"ty":"gr","it":[{"ind":0,"ty":"sh","ix":1,"ks":{"a":0,"k":{"i":[[0,0],[0,0],[0,0]],"o":[[0,0],[0,0],[0,0]],"v":[[-4.025,-8.668],[-8.669,8.668],[8.669,4.025]],"c":true},"ix":2},"nm":"パス 1","mn":"ADBE Vector Shape - Group","hd":false},{"ty":"fl","c":{"a":0,"k":[0.047058827269,0.188235309077,0.588235294118,1],"ix":4},"o":{"a":0,"k":100,"ix":5},"r":1,"bm":0,"nm":"塗り 1","mn":"ADBE Vector Graphic - Fill","hd":false},{"ty":"tr","p":{"a":0,"k":[8.918,125.299],"ix":2},"a":{"a":0,"k":[0,0],"ix":1},"s":{"a":0,"k":[100,100],"ix":3},"r":{"a":0,"k":0,"ix":6},"o":{"a":1,"k":[{"i":{"x":[0.833],"y":[0.833]},"o":{"x":[0.167],"y":[0.167]},"t":22,"s":[0]},{"t":24.00000097754,"s":[100]}],"ix":7},"sk":{"a":0,"k":0,"ix":4},"sa":{"a":0,"k":0,"ix":5},"nm":"トランスフォーム"}],"nm":"グループ 1","np":2,"cix":2,"bm":0,"ix":1,"mn":"ADBE Vector Group","hd":false},{"ty":"gr","it":[{"ind":0,"ty":"sh","ix":1,"ks":{"a":0,"k":{"i":[[0,0],[0,0]],"o":[[0,0],[0,0]],"v":[[0.354,-0.354],[-0.354,0.354]],"c":false},"ix":2},"nm":"パス 1","mn":"ADBE Vector Shape - Group","hd":false},{"ty":"st","c":{"a":0,"k":[0.047058827269,0.188235309077,0.588235294118,1],"ix":3},"o":{"a":0,"k":100,"ix":4},"w":{"a":0,"k":2,"ix":5},"lc":1,"lj":2,"bm":0,"nm":"線 1","mn":"ADBE Vector Graphic - Stroke","hd":false},{"ty":"tr","p":{"a":0,"k":[9.737,124.481],"ix":2},"a":{"a":0,"k":[0,0],"ix":1},"s":{"a":0,"k":[100,100],"ix":3},"r":{"a":0,"k":0,"ix":6},"o":{"a":0,"k":100,"ix":7},"sk":{"a":0,"k":0,"ix":4},"sa":{"a":0,"k":0,"ix":5},"nm":"トランスフォーム"}],"nm":"グループ 2","np":2,"cix":2,"bm":0,"ix":2,"mn":"ADBE Vector Group","hd":false},{"ty":"gr","it":[{"ind":0,"ty":"sh","ix":1,"ks":{"a":0,"k":{"i":[[0,0],[0,0]],"o":[[0,0],[0,0]],"v":[[55.021,-55.021],[-55.021,55.021]],"c":false},"ix":2},"nm":"パス 1","mn":"ADBE Vector Shape - Group","hd":false},{"ty":"st","c":{"a":0,"k":[0.047058827269,0.188235309077,0.588235294118,1],"ix":3},"o":{"a":0,"k":100,"ix":4},"w":{"a":0,"k":2,"ix":5},"lc":1,"lj":2,"bm":0,"d":[{"n":"d","nm":"線分","v":{"a":0,"k":1.945,"ix":1}},{"n":"g","nm":"間隔","v":{"a":0,"k":3.891,"ix":2}},{"n":"d","nm":"線分2","v":{"a":0,"k":1.945,"ix":3}},{"n":"g","nm":"間隔2","v":{"a":0,"k":3.891,"ix":4}},{"n":"d","nm":"線分3","v":{"a":0,"k":1.945,"ix":5}},{"n":"g","nm":"間隔3","v":{"a":0,"k":3.891,"ix":6}},{"n":"o","nm":"オフセット","v":{"a":0,"k":0,"ix":7}}],"nm":"線 1","mn":"ADBE Vector Graphic - Stroke","hd":false},{"ty":"tr","p":{"a":0,"k":[66.486,67.732],"ix":2},"a":{"a":0,"k":[0,0],"ix":1},"s":{"a":0,"k":[100,100],"ix":3},"r":{"a":0,"k":0,"ix":6},"o":{"a":0,"k":100,"ix":7},"sk":{"a":0,"k":0,"ix":4},"sa":{"a":0,"k":0,"ix":5},"nm":"トランスフォーム"}],"nm":"グループ 3","np":2,"cix":2,"bm":0,"ix":3,"mn":"ADBE Vector Group","hd":false},{"ty":"tm","s":{"a":0,"k":0,"ix":1},"e":{"a":1,"k":[{"i":{"x":[0.667],"y":[1]},"o":{"x":[0.333],"y":[0]},"t":3,"s":[0]},{"t":24.00000097754,"s":[100]}],"ix":2},"o":{"a":0,"k":0,"ix":3},"m":1,"ix":4,"nm":"パスのトリミング 1","mn":"ADBE Vector Filter - Trim","hd":false}],"ip":0,"op":151.000006150356,"st":0,"bm":0},{"ddd":0,"ind":2,"ty":5,"nm":"text1","sr":1,"ks":{"o":{"a":1,"k":[{"i":{"x":[0.833],"y":[0.833]},"o":{"x":[0.167],"y":[0.167]},"t":21,"s":[0]},{"t":24.00000097754,"s":[100]}],"ix":11},"r":{"a":0,"k":-45,"ix":10},"p":{"a":0,"k":[301.39,337.957,0],"ix":2,"l":2},"a":{"a":0,"k":[0,0,0],"ix":1,"l":2},"s":{"a":0,"k":[100,100,100],"ix":6,"l":2}},"ao":0,"t":{"d":{"k":[{"s":{"s":16,"f":"NotoSansJP-Bold","t":"広告・サービス","ca":0,"j":2,"tr":75,"lh":19.2000007629395,"ls":0,"fc":[0.047,0.188,0.588]},"t":0}]},"p":{},"m":{"g":1,"a":{"a":0,"k":[0,0],"ix":2}},"a":[]},"ip":0,"op":151.000006150356,"st":0,"bm":0},{"ddd":0,"ind":3,"ty":4,"nm":"border2","sr":1,"ks":{"o":{"a":0,"k":100,"ix":11},"r":{"a":0,"k":0,"ix":10},"p":{"a":0,"k":[339,370.5,0],"ix":2,"l":2},"a":{"a":0,"k":[67.5,67.5,0],"ix":1,"l":2},"s":{"a":0,"k":[100,100,100],"ix":6,"l":2}},"ao":0,"shapes":[{"ty":"gr","it":[{"ind":0,"ty":"sh","ix":1,"ks":{"a":0,"k":{"i":[[0,0],[0,0],[0,0]],"o":[[0,0],[0,0],[0,0]],"v":[[-8.668,-4.024],[4.025,8.669],[8.668,-8.669]],"c":true},"ix":2},"nm":"パス 1","mn":"ADBE Vector Shape - Group","hd":false},{"ty":"fl","c":{"a":0,"k":[0.047058827269,0.188235309077,0.588235294118,1],"ix":4},"o":{"a":0,"k":100,"ix":5},"r":1,"bm":0,"nm":"塗り 1","mn":"ADBE Vector Graphic - Fill","hd":false},{"ty":"tr","p":{"a":0,"k":[116.299,17.919],"ix":2},"a":{"a":0,"k":[0,0],"ix":1},"s":{"a":0,"k":[100,100],"ix":3},"r":{"a":0,"k":0,"ix":6},"o":{"a":1,"k":[{"i":{"x":[0.833],"y":[0.833]},"o":{"x":[0.167],"y":[0.167]},"t":45,"s":[0]},{"t":46.0000018736184,"s":[100]}],"ix":7},"sk":{"a":0,"k":0,"ix":4},"sa":{"a":0,"k":0,"ix":5},"nm":"トランスフォーム"}],"nm":"グループ 1","np":2,"cix":2,"bm":0,"ix":1,"mn":"ADBE Vector Group","hd":false},{"ty":"gr","it":[{"ind":0,"ty":"sh","ix":1,"ks":{"a":0,"k":{"i":[[0,0],[0,0]],"o":[[0,0],[0,0]],"v":[[-0.354,0.354],[0.354,-0.354]],"c":false},"ix":2},"nm":"パス 1","mn":"ADBE Vector Shape - Group","hd":false},{"ty":"st","c":{"a":0,"k":[0.047058827269,0.188235309077,0.588235294118,1],"ix":3},"o":{"a":0,"k":100,"ix":4},"w":{"a":0,"k":2,"ix":5},"lc":1,"lj":2,"bm":0,"nm":"線 1","mn":"ADBE Vector Graphic - Stroke","hd":false},{"ty":"tr","p":{"a":0,"k":[1.354,132.864],"ix":2},"a":{"a":0,"k":[0,0],"ix":1},"s":{"a":0,"k":[100,100],"ix":3},"r":{"a":0,"k":0,"ix":6},"o":{"a":0,"k":100,"ix":7},"sk":{"a":0,"k":0,"ix":4},"sa":{"a":0,"k":0,"ix":5},"nm":"トランスフォーム"}],"nm":"グループ 2","np":2,"cix":2,"bm":0,"ix":2,"mn":"ADBE Vector Group","hd":false},{"ty":"gr","it":[{"ind":0,"ty":"sh","ix":1,"ks":{"a":0,"k":{"i":[[0,0],[0,0]],"o":[[0,0],[0,0]],"v":[[-55.02,55.021],[55.02,-55.021]],"c":false},"ix":2},"nm":"パス 1","mn":"ADBE Vector Shape - Group","hd":false},{"ty":"st","c":{"a":0,"k":[0.047058827269,0.188235309077,0.588235294118,1],"ix":3},"o":{"a":0,"k":100,"ix":4},"w":{"a":0,"k":2,"ix":5},"lc":1,"lj":2,"bm":0,"d":[{"n":"d","nm":"線分","v":{"a":0,"k":1.945,"ix":1}},{"n":"g","nm":"間隔","v":{"a":0,"k":3.891,"ix":2}},{"n":"d","nm":"線分2","v":{"a":0,"k":1.945,"ix":3}},{"n":"g","nm":"間隔2","v":{"a":0,"k":3.891,"ix":4}},{"n":"d","nm":"線分3","v":{"a":0,"k":1.945,"ix":5}},{"n":"g","nm":"間隔3","v":{"a":0,"k":3.891,"ix":6}},{"n":"o","nm":"オフセット","v":{"a":0,"k":0,"ix":7}}],"nm":"線 1","mn":"ADBE Vector Graphic - Stroke","hd":false},{"ty":"tr","p":{"a":0,"k":[58.103,76.115],"ix":2},"a":{"a":0,"k":[0,0],"ix":1},"s":{"a":0,"k":[100,100],"ix":3},"r":{"a":0,"k":0,"ix":6},"o":{"a":0,"k":100,"ix":7},"sk":{"a":0,"k":0,"ix":4},"sa":{"a":0,"k":0,"ix":5},"nm":"トランスフォーム"}],"nm":"グループ 3","np":2,"cix":2,"bm":0,"ix":3,"mn":"ADBE Vector Group","hd":false},{"ty":"tm","s":{"a":0,"k":0,"ix":1},"e":{"a":1,"k":[{"i":{"x":[0.833],"y":[0.833]},"o":{"x":[0.167],"y":[0.167]},"t":18,"s":[0]},{"t":45.0000018328876,"s":[100]}],"ix":2},"o":{"a":0,"k":0,"ix":3},"m":1,"ix":4,"nm":"パスのトリミング 1","mn":"ADBE Vector Filter - Trim","hd":false}],"ip":0,"op":151.000006150356,"st":0,"bm":0},{"ddd":0,"ind":4,"ty":5,"nm":"text2","sr":1,"ks":{"o":{"a":1,"k":[{"i":{"x":[0.833],"y":[0.833]},"o":{"x":[0.167],"y":[0.167]},"t":43,"s":[0]},{"t":46.0000018736184,"s":[100]}],"ix":11},"r":{"a":0,"k":-45,"ix":10},"p":{"a":0,"k":[358.929,387.965,0],"ix":2,"l":2},"a":{"a":0,"k":[0,0,0],"ix":1,"l":2},"s":{"a":0,"k":[100,100,100],"ix":6,"l":2}},"ao":0,"t":{"d":{"k":[{"s":{"s":16,"f":"NotoSansJP-Bold","t":"掲載料","ca":0,"j":2,"tr":75,"lh":19.2000007629395,"ls":0,"fc":[0.047,0.188,0.588]},"t":0}]},"p":{},"m":{"g":1,"a":{"a":0,"k":[0,0],"ix":2}},"a":[]},"ip":0,"op":151.000006150356,"st":0,"bm":0},{"ddd":0,"ind":5,"ty":4,"nm":"border3","sr":1,"ks":{"o":{"a":0,"k":100,"ix":11},"r":{"a":0,"k":0,"ix":10},"p":{"a":0,"k":[591,352.5,0],"ix":2,"l":2},"a":{"a":0,"k":[67.5,67.5,0],"ix":1,"l":2},"s":{"a":0,"k":[100,100,100],"ix":6,"l":2}},"ao":0,"shapes":[{"ty":"gr","it":[{"ind":0,"ty":"sh","ix":1,"ks":{"a":0,"k":{"i":[[0,0],[0,0],[0,0]],"o":[[0,0],[0,0],[0,0]],"v":[[-8.668,4.024],[8.668,8.669],[4.025,-8.669]],"c":true},"ix":2},"nm":"パス 1","mn":"ADBE Vector Shape - Group","hd":false},{"ty":"fl","c":{"a":0,"k":[0.047058827269,0.188235309077,0.588235294118,1],"ix":4},"o":{"a":0,"k":100,"ix":5},"r":1,"bm":0,"nm":"塗り 1","mn":"ADBE Vector Graphic - Fill","hd":false},{"ty":"tr","p":{"a":0,"k":[125.299,125.299],"ix":2},"a":{"a":0,"k":[0,0],"ix":1},"s":{"a":0,"k":[100,100],"ix":3},"r":{"a":0,"k":0,"ix":6},"o":{"a":1,"k":[{"i":{"x":[0.833],"y":[0.833]},"o":{"x":[0.167],"y":[0.167]},"t":39,"s":[0]},{"t":41.0000016699642,"s":[100]}],"ix":7},"sk":{"a":0,"k":0,"ix":4},"sa":{"a":0,"k":0,"ix":5},"nm":"トランスフォーム"}],"nm":"グループ 1","np":2,"cix":2,"bm":0,"ix":1,"mn":"ADBE Vector Group","hd":false},{"ty":"gr","it":[{"ind":0,"ty":"sh","ix":1,"ks":{"a":0,"k":{"i":[[0,0],[0,0]],"o":[[0,0],[0,0]],"v":[[-0.353,-0.354],[0.353,0.354]],"c":false},"ix":2},"nm":"パス 1","mn":"ADBE Vector Shape - Group","hd":false},{"ty":"st","c":{"a":0,"k":[0.047058827269,0.188235309077,0.588235294118,1],"ix":3},"o":{"a":0,"k":100,"ix":4},"w":{"a":0,"k":2,"ix":5},"lc":1,"lj":2,"bm":0,"nm":"線 1","mn":"ADBE Vector Graphic - Stroke","hd":false},{"ty":"tr","p":{"a":0,"k":[124.481,124.481],"ix":2},"a":{"a":0,"k":[0,0],"ix":1},"s":{"a":0,"k":[100,100],"ix":3},"r":{"a":0,"k":0,"ix":6},"o":{"a":0,"k":100,"ix":7},"sk":{"a":0,"k":0,"ix":4},"sa":{"a":0,"k":0,"ix":5},"nm":"トランスフォーム"}],"nm":"グループ 2","np":2,"cix":2,"bm":0,"ix":2,"mn":"ADBE Vector Group","hd":false},{"ty":"gr","it":[{"ind":0,"ty":"sh","ix":1,"ks":{"a":0,"k":{"i":[[0,0],[0,0]],"o":[[0,0],[0,0]],"v":[[-55.021,-55.021],[55.021,55.021]],"c":false},"ix":2},"nm":"パス 1","mn":"ADBE Vector Shape - Group","hd":false},{"ty":"st","c":{"a":0,"k":[0.047058827269,0.188235309077,0.588235294118,1],"ix":3},"o":{"a":0,"k":100,"ix":4},"w":{"a":0,"k":2,"ix":5},"lc":1,"lj":2,"bm":0,"d":[{"n":"d","nm":"線分","v":{"a":0,"k":1.945,"ix":1}},{"n":"g","nm":"間隔","v":{"a":0,"k":3.891,"ix":2}},{"n":"d","nm":"線分2","v":{"a":0,"k":1.945,"ix":3}},{"n":"g","nm":"間隔2","v":{"a":0,"k":3.891,"ix":4}},{"n":"d","nm":"線分3","v":{"a":0,"k":1.945,"ix":5}},{"n":"g","nm":"間隔3","v":{"a":0,"k":3.891,"ix":6}},{"n":"o","nm":"オフセット","v":{"a":0,"k":0,"ix":7}}],"nm":"線 1","mn":"ADBE Vector Graphic - Stroke","hd":false},{"ty":"tr","p":{"a":0,"k":[67.732,67.732],"ix":2},"a":{"a":0,"k":[0,0],"ix":1},"s":{"a":0,"k":[100,100],"ix":3},"r":{"a":0,"k":0,"ix":6},"o":{"a":0,"k":100,"ix":7},"sk":{"a":0,"k":0,"ix":4},"sa":{"a":0,"k":0,"ix":5},"nm":"トランスフォーム"}],"nm":"グループ 3","np":2,"cix":2,"bm":0,"ix":3,"mn":"ADBE Vector Group","hd":false},{"ty":"tm","s":{"a":0,"k":0,"ix":1},"e":{"a":1,"k":[{"i":{"x":[0.833],"y":[0.833]},"o":{"x":[0.167],"y":[0.167]},"t":3,"s":[0]},{"t":41.0000016699642,"s":[100]}],"ix":2},"o":{"a":0,"k":0,"ix":3},"m":1,"ix":4,"nm":"パスのトリミング 1","mn":"ADBE Vector Filter - Trim","hd":false}],"ip":0,"op":151.000006150356,"st":0,"bm":0},{"ddd":0,"ind":6,"ty":5,"nm":"text3","sr":1,"ks":{"o":{"a":1,"k":[{"i":{"x":[0.833],"y":[0.833]},"o":{"x":[0.167],"y":[0.167]},"t":43,"s":[0]},{"t":46.0000018736184,"s":[100]}],"ix":11},"r":{"a":0,"k":45,"ix":10},"p":{"a":0,"k":[600.634,340.388,0],"ix":2,"l":2},"a":{"a":0,"k":[0,0,0],"ix":1,"l":2},"s":{"a":0,"k":[100,100,100],"ix":6,"l":2}},"ao":0,"t":{"d":{"k":[{"s":{"s":16,"f":"NotoSansJP-Bold","t":"メディア","ca":0,"j":2,"tr":75,"lh":19.2000007629395,"ls":0,"fc":[0.047,0.188,0.588]},"t":0}]},"p":{},"m":{"g":1,"a":{"a":0,"k":[0,0],"ix":2}},"a":[]},"ip":0,"op":151.000006150356,"st":0,"bm":0},{"ddd":0,"ind":7,"ty":4,"nm":"border4","sr":1,"ks":{"o":{"a":0,"k":100,"ix":11},"r":{"a":0,"k":0,"ix":10},"p":{"a":0,"k":[561,370.5,0],"ix":2,"l":2},"a":{"a":0,"k":[67.5,67.5,0],"ix":1,"l":2},"s":{"a":0,"k":[100,100,100],"ix":6,"l":2}},"ao":0,"shapes":[{"ty":"gr","it":[{"ind":0,"ty":"sh","ix":1,"ks":{"a":0,"k":{"i":[[0,0],[0,0],[0,0]],"o":[[0,0],[0,0],[0,0]],"v":[[-4.024,8.668],[8.668,-4.025],[-8.668,-8.668]],"c":true},"ix":2},"nm":"パス 1","mn":"ADBE Vector Shape - Group","hd":false},{"ty":"fl","c":{"a":0,"k":[0.047058827269,0.188235309077,0.588235294118,1],"ix":4},"o":{"a":0,"k":100,"ix":5},"r":1,"bm":0,"nm":"塗り 1","mn":"ADBE Vector Graphic - Fill","hd":false},{"ty":"tr","p":{"a":0,"k":[16.918,16.918],"ix":2},"a":{"a":0,"k":[0,0],"ix":1},"s":{"a":0,"k":[100,100],"ix":3},"r":{"a":0,"k":0,"ix":6},"o":{"a":1,"k":[{"i":{"x":[0.833],"y":[0.833]},"o":{"x":[0.167],"y":[0.167]},"t":56,"s":[0]},{"t":57.0000023216576,"s":[100]}],"ix":7},"sk":{"a":0,"k":0,"ix":4},"sa":{"a":0,"k":0,"ix":5},"nm":"トランスフォーム"}],"nm":"グループ 1","np":2,"cix":2,"bm":0,"ix":1,"mn":"ADBE Vector Group","hd":false},{"ty":"gr","it":[{"ind":0,"ty":"sh","ix":1,"ks":{"a":0,"k":{"i":[[0,0],[0,0]],"o":[[0,0],[0,0]],"v":[[0.353,0.354],[-0.353,-0.354]],"c":false},"ix":2},"nm":"パス 1","mn":"ADBE Vector Shape - Group","hd":false},{"ty":"st","c":{"a":0,"k":[0.047058827269,0.188235309077,0.588235294118,1],"ix":3},"o":{"a":0,"k":100,"ix":4},"w":{"a":0,"k":2,"ix":5},"lc":1,"lj":2,"bm":0,"nm":"線 1","mn":"ADBE Vector Graphic - Stroke","hd":false},{"ty":"tr","p":{"a":0,"k":[132.864,132.863],"ix":2},"a":{"a":0,"k":[0,0],"ix":1},"s":{"a":0,"k":[100,100],"ix":3},"r":{"a":0,"k":0,"ix":6},"o":{"a":0,"k":100,"ix":7},"sk":{"a":0,"k":0,"ix":4},"sa":{"a":0,"k":0,"ix":5},"nm":"トランスフォーム"}],"nm":"グループ 2","np":2,"cix":2,"bm":0,"ix":2,"mn":"ADBE Vector Group","hd":false},{"ty":"gr","it":[{"ind":0,"ty":"sh","ix":1,"ks":{"a":0,"k":{"i":[[0,0],[0,0]],"o":[[0,0],[0,0]],"v":[[55.021,55.021],[-55.021,-55.021]],"c":false},"ix":2},"nm":"パス 1","mn":"ADBE Vector Shape - Group","hd":false},{"ty":"st","c":{"a":0,"k":[0.047058827269,0.188235309077,0.588235294118,1],"ix":3},"o":{"a":0,"k":100,"ix":4},"w":{"a":0,"k":2,"ix":5},"lc":1,"lj":2,"bm":0,"d":[{"n":"d","nm":"線分","v":{"a":0,"k":1.945,"ix":1}},{"n":"g","nm":"間隔","v":{"a":0,"k":3.891,"ix":2}},{"n":"d","nm":"線分2","v":{"a":0,"k":1.945,"ix":3}},{"n":"g","nm":"間隔2","v":{"a":0,"k":3.891,"ix":4}},{"n":"d","nm":"線分3","v":{"a":0,"k":1.945,"ix":5}},{"n":"g","nm":"間隔3","v":{"a":0,"k":3.891,"ix":6}},{"n":"o","nm":"オフセット","v":{"a":0,"k":0,"ix":7}}],"nm":"線 1","mn":"ADBE Vector Graphic - Stroke","hd":false},{"ty":"tr","p":{"a":0,"k":[76.115,76.114],"ix":2},"a":{"a":0,"k":[0,0],"ix":1},"s":{"a":0,"k":[100,100],"ix":3},"r":{"a":0,"k":0,"ix":6},"o":{"a":0,"k":100,"ix":7},"sk":{"a":0,"k":0,"ix":4},"sa":{"a":0,"k":0,"ix":5},"nm":"トランスフォーム"}],"nm":"グループ 3","np":2,"cix":2,"bm":0,"ix":3,"mn":"ADBE Vector Group","hd":false},{"ty":"tm","s":{"a":0,"k":0,"ix":1},"e":{"a":1,"k":[{"i":{"x":[0.833],"y":[0.833]},"o":{"x":[0.167],"y":[0.167]},"t":34,"s":[0]},{"t":57.0000023216576,"s":[100]}],"ix":2},"o":{"a":0,"k":0,"ix":3},"m":1,"ix":4,"nm":"パスのトリミング 1","mn":"ADBE Vector Filter - Trim","hd":false}],"ip":0,"op":151.000006150356,"st":0,"bm":0},{"ddd":0,"ind":8,"ty":5,"nm":"text4","sr":1,"ks":{"o":{"a":1,"k":[{"i":{"x":[0.833],"y":[0.833]},"o":{"x":[0.167],"y":[0.167]},"t":53,"s":[0]},{"t":56.0000022809268,"s":[100]}],"ix":11},"r":{"a":0,"k":45,"ix":10},"p":{"a":0,"k":[541.647,390.617,0],"ix":2,"l":2},"a":{"a":0,"k":[0,0,0],"ix":1,"l":2},"s":{"a":0,"k":[100,100,100],"ix":6,"l":2}},"ao":0,"t":{"d":{"k":[{"s":{"s":16,"f":"NotoSansJP-Bold","t":"サービス利用","ca":0,"j":2,"tr":75,"lh":19.2000007629395,"ls":0,"fc":[0.047,0.188,0.588]},"t":0}]},"p":{},"m":{"g":1,"a":{"a":0,"k":[0,0],"ix":2}},"a":[]},"ip":0,"op":151.000006150356,"st":0,"bm":0},{"ddd":0,"ind":9,"ty":4,"nm":"border5","sr":1,"ks":{"o":{"a":0,"k":100,"ix":11},"r":{"a":0,"k":0,"ix":10},"p":{"a":0,"k":[451,521.473,0],"ix":2,"l":2},"a":{"a":0,"k":[158,9.5,0],"ix":1,"l":2},"s":{"a":0,"k":[100,100,100],"ix":6,"l":2}},"ao":0,"shapes":[{"ty":"gr","it":[{"ind":0,"ty":"sh","ix":1,"ks":{"a":0,"k":{"i":[[0,0],[0,0],[0,0]],"o":[[0,0],[0,0],[0,0]],"v":[[7.771,-8.975],[-7.771,0],[7.771,8.975]],"c":true},"ix":2},"nm":"パス 1","mn":"ADBE Vector Shape - Group","hd":false},{"ty":"fl","c":{"a":0,"k":[0.047058827269,0.188235309077,0.588235294118,1],"ix":4},"o":{"a":0,"k":100,"ix":5},"r":1,"bm":0,"nm":"塗り 1","mn":"ADBE Vector Graphic - Fill","hd":false},{"ty":"tr","p":{"a":0,"k":[8.021,9.225],"ix":2},"a":{"a":0,"k":[0,0],"ix":1},"s":{"a":0,"k":[100,100],"ix":3},"r":{"a":0,"k":0,"ix":6},"o":{"a":1,"k":[{"i":{"x":[0.833],"y":[0.833]},"o":{"x":[0.167],"y":[0.167]},"t":79,"s":[0]},{"t":82.0000033399285,"s":[100]}],"ix":7},"sk":{"a":0,"k":0,"ix":4},"sa":{"a":0,"k":0,"ix":5},"nm":"トランスフォーム"}],"nm":"グループ 1","np":2,"cix":2,"bm":0,"ix":1,"mn":"ADBE Vector Group","hd":false},{"ty":"gr","it":[{"ind":0,"ty":"sh","ix":1,"ks":{"a":0,"k":{"i":[[0,0],[0,0]],"o":[[0,0],[0,0]],"v":[[314.871,9.225],[13.167,9.225]],"c":false},"ix":2},"nm":"パス 1","mn":"ADBE Vector Shape - Group","hd":false},{"ty":"st","c":{"a":0,"k":[0.047058827269,0.188235309077,0.588235294118,1],"ix":3},"o":{"a":0,"k":100,"ix":4},"w":{"a":0,"k":2,"ix":5},"lc":1,"lj":2,"bm":0,"d":[{"n":"d","nm":"線分","v":{"a":0,"k":2,"ix":1}},{"n":"g","nm":"間隔","v":{"a":0,"k":4,"ix":2}},{"n":"d","nm":"線分2","v":{"a":0,"k":2,"ix":3}},{"n":"g","nm":"間隔2","v":{"a":0,"k":4,"ix":4}},{"n":"d","nm":"線分3","v":{"a":0,"k":2,"ix":5}},{"n":"g","nm":"間隔3","v":{"a":0,"k":4,"ix":6}},{"n":"o","nm":"オフセット","v":{"a":0,"k":0,"ix":7}}],"nm":"線 1","mn":"ADBE Vector Graphic - Stroke","hd":false},{"ty":"tr","p":{"a":0,"k":[0,0],"ix":2},"a":{"a":0,"k":[0,0],"ix":1},"s":{"a":0,"k":[100,100],"ix":3},"r":{"a":0,"k":0,"ix":6},"o":{"a":0,"k":100,"ix":7},"sk":{"a":0,"k":0,"ix":4},"sa":{"a":0,"k":0,"ix":5},"nm":"トランスフォーム"}],"nm":"グループ 2","np":2,"cix":2,"bm":0,"ix":2,"mn":"ADBE Vector Group","hd":false},{"ty":"tm","s":{"a":0,"k":0,"ix":1},"e":{"a":1,"k":[{"i":{"x":[0.64],"y":[0.975]},"o":{"x":[0.359],"y":[0.022]},"t":34,"s":[0]},{"t":82.0000033399285,"s":[100]}],"ix":2},"o":{"a":0,"k":0,"ix":3},"m":1,"ix":3,"nm":"パスのトリミング 1","mn":"ADBE Vector Filter - Trim","hd":false}],"ip":0,"op":151.000006150356,"st":0,"bm":0},{"ddd":0,"ind":10,"ty":4,"nm":"text5","sr":1,"ks":{"o":{"a":1,"k":[{"i":{"x":[0.833],"y":[0.833]},"o":{"x":[0.167],"y":[0.167]},"t":83,"s":[0]},{"t":86.0000035028518,"s":[100]}],"ix":11},"r":{"a":0,"k":0,"ix":10},"p":{"a":0,"k":[452.674,545.092,0],"ix":2,"l":2},"a":{"a":0,"k":[0,0,0],"ix":1,"l":2},"s":{"a":0,"k":[100,100,100],"ix":6,"l":2}},"ao":0,"shapes":[{"ty":"gr","it":[{"ind":0,"ty":"sh","ix":1,"ks":{"a":0,"k":{"i":[[0,0],[0,0],[0,0],[0,0],[0.564,0.87]],"o":[[0,0],[0,0],[0,0],[-0.209,-0.79],[0,0]],"v":[[-31.359,-10.055],[-31.359,-6.655],[-34.146,-6.655],[-32.615,-7.251],[-33.985,-10.055]],"c":true},"ix":2},"nm":"来","mn":"ADBE Vector Shape - Group","hd":false},{"ind":1,"ty":"sh","ix":2,"ks":{"a":0,"k":{"i":[[0,0],[0.467,-0.79],[0,0],[0,0],[0,0]],"o":[[-0.322,0.935],[0,0],[0,0],[0,0],[0,0]],"v":[[-26.605,-10.055],[-27.975,-7.122],[-26.621,-6.655],[-29.328,-6.655],[-29.328,-10.055]],"c":true},"ix":2},"nm":"来","mn":"ADBE Vector Shape - Group","hd":false},{"ind":2,"ty":"sh","ix":3,"ks":{"a":0,"k":{"i":[[0,0],[0,0],[0,0],[-0.564,1.047],[0,0],[0,0],[0,0],[0,0],[0,0],[0,0],[0,0],[0,0],[0,0],[0,0],[0,0],[-0.177,-0.773],[0,0],[0,0],[0,0],[2.03,-0.838],[-0.306,-0.467],[-1.466,1.805],[0,0],[0,0],[0,0],[-1.934,-0.967],[-0.435,0.387],[1.386,1.676]],"o":[[0,0],[0,0],[0.516,-0.725],[0,0],[0,0],[0,0],[0,0],[0,0],[0,0],[0,0],[0,0],[0,0],[0,0],[0,0],[0.516,0.87],[0,0],[0,0],[0,0],[-1.402,1.66],[0.451,0.387],[1.934,-0.967],[0,0],[0,0],[0,0],[1.45,1.837],[0.29,-0.467],[-2.014,-0.838],[0,0]],"v":[[-23.141,-4.818],[-23.141,-6.655],[-26.267,-6.655],[-24.575,-9.507],[-26.428,-10.055],[-23.753,-10.055],[-23.753,-11.892],[-29.328,-11.892],[-29.328,-13.648],[-31.359,-13.648],[-31.359,-11.892],[-36.789,-11.892],[-36.789,-10.055],[-34.049,-10.055],[-35.709,-9.426],[-34.501,-6.655],[-37.546,-6.655],[-37.546,-4.818],[-32.486,-4.818],[-37.997,-0.79],[-36.644,0.822],[-31.359,-3.529],[-31.359,1.386],[-29.328,1.386],[-29.328,-3.561],[-24.059,0.854],[-22.722,-0.757],[-28.184,-4.818]],"c":true},"ix":2},"nm":"来","mn":"ADBE Vector Shape - Group","hd":false},{"ty":"mm","mm":1,"nm":"パスを結合 1","mn":"ADBE Vector Filter - Merge","hd":false},{"ty":"fl","c":{"a":0,"k":[0.047059997858,0.188240006391,0.588239961512,1],"ix":4},"o":{"a":0,"k":100,"ix":5},"r":1,"bm":0,"nm":"塗り 1","mn":"ADBE Vector Graphic - Fill","hd":false},{"ty":"tr","p":{"a":0,"k":[0,0],"ix":2},"a":{"a":0,"k":[0,0],"ix":1},"s":{"a":0,"k":[100,100],"ix":3},"r":{"a":0,"k":0,"ix":6},"o":{"a":0,"k":100,"ix":7},"sk":{"a":0,"k":0,"ix":4},"sa":{"a":0,"k":0,"ix":5},"nm":"トランスフォーム"}],"nm":"来","np":6,"cix":2,"bm":0,"ix":1,"mn":"ADBE Vector Group","hd":false},{"ty":"gr","it":[{"ind":0,"ty":"sh","ix":1,"ks":{"a":0,"k":{"i":[[0,0],[0,0],[0,0],[0,0]],"o":[[0,0],[0,0],[0,0],[0,0]],"v":[[-8.906,-0.87],[-14.626,-0.87],[-14.626,-3.062],[-8.906,-3.062]],"c":true},"ix":2},"nm":"店","mn":"ADBE Vector Shape - Group","hd":false},{"ind":1,"ty":"sh","ix":2,"ks":{"a":0,"k":{"i":[[0,0],[0,0],[0,0],[0,0],[0,0],[0,0],[0,0],[0,0],[0,0],[0,0],[0,0],[0,0],[0,0],[0,0],[0,0],[0,0]],"o":[[0,0],[0,0],[0,0],[0,0],[0,0],[0,0],[0,0],[0,0],[0,0],[0,0],[0,0],[0,0],[0,0],[0,0],[0,0],[0,0]],"v":[[-11.016,-9.716],[-12.966,-9.716],[-12.966,-4.753],[-16.495,-4.753],[-16.495,1.402],[-14.626,1.402],[-14.626,0.806],[-8.906,0.806],[-8.906,1.386],[-6.94,1.386],[-6.94,-4.753],[-11.016,-4.753],[-11.016,-6.51],[-5.989,-6.51],[-5.989,-8.202],[-11.016,-8.202]],"c":true},"ix":2},"nm":"店","mn":"ADBE Vector Shape - Group","hd":false},{"ind":2,"ty":"sh","ix":3,"ks":{"a":0,"k":{"i":[[0,0],[0,0],[0,0],[0,0],[0,0],[0,0],[1.321,-2.304],[-0.354,-0.322],[0,2.594],[0,0],[0,0],[0,0]],"o":[[0,0],[0,0],[0,0],[0,0],[0,0],[0,2.32],[0.451,0.209],[1.45,-2.514],[0,0],[0,0],[0,0],[0,0]],"v":[[-11.645,-11.779],[-11.645,-13.632],[-13.643,-13.632],[-13.643,-11.779],[-19.379,-11.779],[-19.379,-7.718],[-20.813,0.29],[-19.154,1.37],[-17.462,-7.718],[-17.462,-9.958],[-5.78,-9.958],[-5.78,-11.779]],"c":true},"ix":2},"nm":"店","mn":"ADBE Vector Shape - Group","hd":false},{"ty":"mm","mm":1,"nm":"パスを結合 1","mn":"ADBE Vector Filter - Merge","hd":false},{"ty":"fl","c":{"a":0,"k":[0.047059997858,0.188240006391,0.588239961512,1],"ix":4},"o":{"a":0,"k":100,"ix":5},"r":1,"bm":0,"nm":"塗り 1","mn":"ADBE Vector Graphic - Fill","hd":false},{"ty":"tr","p":{"a":0,"k":[0,0],"ix":2},"a":{"a":0,"k":[0,0],"ix":1},"s":{"a":0,"k":[100,100],"ix":3},"r":{"a":0,"k":0,"ix":6},"o":{"a":0,"k":100,"ix":7},"sk":{"a":0,"k":0,"ix":4},"sa":{"a":0,"k":0,"ix":5},"nm":"トランスフォーム"}],"nm":"店","np":6,"cix":2,"bm":0,"ix":2,"mn":"ADBE Vector Group","hd":false},{"ty":"gr","it":[{"ind":0,"ty":"sh","ix":1,"ks":{"a":0,"k":{"i":[[1.128,0],[0,-1.128],[-1.128,0],[0,1.128]],"o":[[-1.128,0],[0,1.128],[1.128,0],[0,-1.128]],"v":[[0.057,-8.186],[-2.006,-6.123],[0.057,-4.061],[2.119,-6.123]],"c":true},"ix":2},"nm":"・","mn":"ADBE Vector Shape - Group","hd":false},{"ty":"fl","c":{"a":0,"k":[0.047059997858,0.188240006391,0.588239961512,1],"ix":4},"o":{"a":0,"k":100,"ix":5},"r":1,"bm":0,"nm":"塗り 1","mn":"ADBE Vector Graphic - Fill","hd":false},{"ty":"tr","p":{"a":0,"k":[0,0],"ix":2},"a":{"a":0,"k":[0,0],"ix":1},"s":{"a":0,"k":[100,100],"ix":3},"r":{"a":0,"k":0,"ix":6},"o":{"a":0,"k":100,"ix":7},"sk":{"a":0,"k":0,"ix":4},"sa":{"a":0,"k":0,"ix":5},"nm":"トランスフォーム"}],"nm":"・","np":3,"cix":2,"bm":0,"ix":3,"mn":"ADBE Vector Group","hd":false},{"ty":"gr","it":[{"ind":0,"ty":"sh","ix":1,"ks":{"a":0,"k":{"i":[[0,0],[-2.369,0.306],[0,0],[-0.161,-0.322],[-0.193,2.723],[0,0],[0.226,-0.274],[0.226,0],[0.58,0.048],[-0.016,-0.532],[-0.403,0.064],[-0.322,0.419],[-0.145,3.867],[0,0],[0,0],[0,0],[0,0],[1.644,-0.967],[0,0],[0.757,-0.081],[0,0],[0,0],[0,0],[0,0],[0,0],[0,0],[0,0],[0,0],[0,0],[0,0],[0,0],[0,0],[0,0],[0,0],[0,0],[0,0],[0,0],[0,0],[0,0],[0.773,-0.064]],"o":[[1.821,-0.209],[0,0],[0.322,0.338],[2.336,-1.257],[0,0],[-0.113,2.594],[-0.145,0.161],[-0.242,0],[0.274,0.435],[0.709,0],[0.467,-0.064],[0.419,-0.532],[0.016,-0.209],[0,0],[0,0],[0,0],[-0.129,2.03],[0,0],[-0.757,0.081],[0,0],[0,0],[0,0],[0,0],[0,0],[0,0],[0,0],[0,0],[0,0],[0,0],[0,0],[0,0],[0,0],[0,0],[0,0],[0,0],[0,0],[0,0],[0,0],[-1.031,0.097],[0,0]],"v":[[6.07,-5.511],[12.757,-6.316],[12.757,-6.542],[13.563,-5.43],[16.689,-11.408],[18.445,-11.408],[17.978,-7.509],[17.478,-7.315],[16.141,-7.364],[16.64,-5.656],[18.429,-5.72],[19.557,-6.349],[20.282,-12.294],[20.298,-13.02],[13.063,-13.02],[13.063,-11.408],[14.9,-11.408],[12.741,-6.929],[12.725,-7.783],[10.437,-7.541],[10.437,-8.685],[12.483,-8.685],[12.483,-10.119],[10.437,-10.119],[10.437,-11.118],[12.693,-11.118],[12.693,-12.552],[10.437,-12.552],[10.437,-13.648],[8.664,-13.648],[8.664,-12.552],[6.183,-12.552],[6.183,-11.118],[8.664,-11.118],[8.664,-10.119],[6.457,-10.119],[6.457,-8.685],[8.664,-8.685],[8.664,-7.348],[5.925,-7.09]],"c":true},"ix":2},"nm":"契","mn":"ADBE Vector Shape - Group","hd":false},{"ind":1,"ty":"sh","ix":2,"ks":{"a":0,"k":{"i":[[0,0],[0,0],[0,0],[0,0],[0,0],[0,0],[0,0],[0,0],[0,0],[4.125,-0.564],[-0.242,-0.467],[-0.79,1.305],[-3.078,-0.371],[-0.419,0.451],[1.047,1.482]],"o":[[0,0],[0,0],[0,0],[0,0],[0,0],[0,0],[0,0],[0,0],[-0.532,1.015],[0.371,0.435],[4.109,-0.58],[1.225,1.789],[0.258,-0.564],[-3.013,-0.177],[0,0]],"v":[[20.427,-2.755],[20.427,-4.367],[14.095,-4.367],[14.095,-5.317],[12.161,-5.317],[12.161,-4.367],[6.118,-4.367],[6.118,-2.755],[11.919,-2.755],[5.716,-0.177],[6.811,1.434],[13.563,-1.644],[19.702,1.418],[20.862,-0.419],[14.932,-2.755]],"c":true},"ix":2},"nm":"契","mn":"ADBE Vector Shape - Group","hd":false},{"ty":"mm","mm":1,"nm":"パスを結合 1","mn":"ADBE Vector Filter - Merge","hd":false},{"ty":"fl","c":{"a":0,"k":[0.047059997858,0.188240006391,0.588239961512,1],"ix":4},"o":{"a":0,"k":100,"ix":5},"r":1,"bm":0,"nm":"塗り 1","mn":"ADBE Vector Graphic - Fill","hd":false},{"ty":"tr","p":{"a":0,"k":[0,0],"ix":2},"a":{"a":0,"k":[0,0],"ix":1},"s":{"a":0,"k":[100,100],"ix":3},"r":{"a":0,"k":0,"ix":6},"o":{"a":0,"k":100,"ix":7},"sk":{"a":0,"k":0,"ix":4},"sa":{"a":0,"k":0,"ix":5},"nm":"トランスフォーム"}],"nm":"契","np":5,"cix":2,"bm":0,"ix":4,"mn":"ADBE Vector Group","hd":false},{"ty":"gr","it":[{"ind":0,"ty":"sh","ix":1,"ks":{"a":0,"k":{"i":[[0,0],[0.467,-0.951],[-0.338,-0.209],[-0.161,1.515]],"o":[[-0.129,1.354],[0.419,0.145],[0.467,-1.031],[0,0]],"v":[[23.544,-4.222],[22.69,-0.483],[24.156,0.209],[25.123,-3.948]],"c":true},"ix":2},"nm":"約","mn":"ADBE Vector Shape - Group","hd":false},{"ind":1,"ty":"sh","ix":2,"ks":{"a":0,"k":{"i":[[0,0],[-0.129,-0.822],[0,0],[0.435,0.951]],"o":[[0.403,0.983],[0,0],[-0.193,-0.822],[0,0]],"v":[[27.137,-3.867],[28.088,-0.757],[29.603,-1.289],[28.555,-4.318]],"c":true},"ix":2},"nm":"約","mn":"ADBE Vector Shape - Group","hd":false},{"ind":2,"ty":"sh","ix":3,"ks":{"a":0,"k":{"i":[[0,0],[-0.209,0.79],[0,0],[1.192,-1.273],[0,0],[0,0],[-0.177,-0.387],[0,0],[-0.902,1.418],[0,0],[0.58,-0.902],[0.209,0.226],[-0.58,1.112],[0,0],[0.451,-0.886],[0.129,0.113],[0,0],[-0.467,-0.693],[0.242,-0.306],[0,0],[0,0],[0,0],[0,0],[0,0],[0,0],[0,0],[-0.048,-0.258],[0,0],[0.564,1.015],[-0.322,-0.29],[-0.435,0.79],[0,0],[0.483,-0.5],[0.306,0],[1.015,0.097],[-0.032,-0.548],[-0.58,0.097],[-0.451,0.612],[-0.209,7.058],[0,0]],"o":[[0.306,-0.741],[0,0],[-0.516,2.03],[0,0],[0,0],[0.193,0.338],[0,0],[1.047,-1.305],[0,0],[-0.387,0.806],[-0.161,-0.209],[0.58,-0.902],[0,0],[-0.274,0.838],[-0.129,-0.113],[0,0],[0.677,0.645],[-0.242,0.354],[0,0],[0,0],[0,0],[0,0],[0,0],[0,0],[0,0],[0.097,0.322],[0,0],[-0.177,-0.806],[0.483,0.29],[0.483,-0.58],[0,0],[-0.177,5.495],[-0.193,0.209],[-0.435,0],[0.354,0.548],[0.935,0.032],[0.677,-0.097],[0.677,-0.854],[0.016,-0.242],[0,0]],"v":[[32.165,-10.925],[32.954,-13.229],[30.988,-13.648],[28.33,-8.282],[28.217,-8.476],[26.863,-7.879],[27.427,-6.768],[25.8,-6.703],[28.878,-11.07],[27.25,-11.747],[25.768,-9.104],[25.204,-9.781],[27.025,-13.036],[25.333,-13.632],[24.156,-10.828],[23.77,-11.167],[22.867,-9.845],[24.801,-7.638],[24.06,-6.639],[22.867,-6.59],[23.028,-4.915],[25.413,-5.076],[25.413,1.418],[27.105,1.418],[27.105,-5.205],[28.024,-5.269],[28.249,-4.399],[29.699,-5.076],[28.442,-8.089],[29.957,-7.025],[31.327,-9.104],[35.774,-9.104],[34.872,-0.757],[34.195,-0.483],[31.826,-0.58],[32.471,1.354],[34.984,1.305],[36.531,0.419],[37.643,-10.039],[37.659,-10.925]],"c":true},"ix":2},"nm":"約","mn":"ADBE Vector Shape - Group","hd":false},{"ind":3,"ty":"sh","ix":4,"ks":{"a":0,"k":{"i":[[0,0],[0.838,1.112],[0,0],[-0.306,-1.015]],"o":[[-0.338,-1.015],[0,0],[0.822,1.16],[0,0]],"v":[[33.985,-3.561],[31.891,-7.17],[30.36,-6.397],[32.326,-2.675]],"c":true},"ix":2},"nm":"約","mn":"ADBE Vector Shape - Group","hd":false},{"ty":"mm","mm":1,"nm":"パスを結合 1","mn":"ADBE Vector Filter - Merge","hd":false},{"ty":"fl","c":{"a":0,"k":[0.047059997858,0.188240006391,0.588239961512,1],"ix":4},"o":{"a":0,"k":100,"ix":5},"r":1,"bm":0,"nm":"塗り 1","mn":"ADBE Vector Graphic - Fill","hd":false},{"ty":"tr","p":{"a":0,"k":[0,0],"ix":2},"a":{"a":0,"k":[0,0],"ix":1},"s":{"a":0,"k":[100,100],"ix":3},"r":{"a":0,"k":0,"ix":6},"o":{"a":0,"k":100,"ix":7},"sk":{"a":0,"k":0,"ix":4},"sa":{"a":0,"k":0,"ix":5},"nm":"トランスフォーム"}],"nm":"約","np":7,"cix":2,"bm":0,"ix":5,"mn":"ADBE Vector Group","hd":false}],"ip":0,"op":151.000006150356,"st":0,"bm":0},{"ddd":0,"ind":13,"ty":4,"nm":"\ncircle","sr":1,"ks":{"o":{"a":1,"k":[{"i":{"x":[0.833],"y":[0.833]},"o":{"x":[0.167],"y":[0.167]},"t":4,"s":[0]},{"t":6.00000024438501,"s":[100]}],"ix":11},"r":{"a":0,"k":0,"ix":10},"p":{"a":0,"k":[451,352.5,0],"ix":2,"l":2},"a":{"a":0,"k":[451,352.5,0],"ix":1,"l":2},"s":{"a":0,"k":[100,100,100],"ix":6,"l":2}},"ao":0,"shapes":[{"ty":"gr","it":[{"ind":0,"ty":"sh","ix":1,"ks":{"a":0,"k":{"i":[[0,-91.002],[-91.002,0],[0,91.002],[91.002,0]],"o":[[0,91.002],[91.002,0],[0,-91.002],[-91.002,0]],"v":[[-164.773,0],[0,164.774],[164.773,0],[0,-164.774]],"c":true},"ix":2},"nm":"パス 1","mn":"ADBE Vector Shape - Group","hd":false},{"ty":"st","c":{"a":0,"k":[0.533333333333,0.647058823529,0.85882358925,1],"ix":3},"o":{"a":0,"k":100,"ix":4},"w":{"a":0,"k":10,"ix":5},"lc":1,"lj":1,"ml":10,"bm":0,"nm":"線 1","mn":"ADBE Vector Graphic - Stroke","hd":false},{"ty":"tm","s":{"a":0,"k":0,"ix":1},"e":{"a":1,"k":[{"i":{"x":[0.556],"y":[0.773]},"o":{"x":[0.619],"y":[0.016]},"t":7,"s":[0]},{"t":44.0000017921567,"s":[100]}],"ix":2},"o":{"a":0,"k":0,"ix":3},"m":1,"ix":3,"nm":"パスのトリミング 1","mn":"ADBE Vector Filter - Trim","hd":false},{"ty":"tr","p":{"a":0,"k":[711.668,514.433],"ix":2},"a":{"a":0,"k":[0,0],"ix":1},"s":{"a":0,"k":[100,100],"ix":3},"r":{"a":0,"k":90,"ix":6},"o":{"a":0,"k":100,"ix":7},"sk":{"a":0,"k":0,"ix":4},"sa":{"a":0,"k":0,"ix":5},"nm":"トランスフォーム"}],"nm":"グループ 1","np":3,"cix":2,"bm":0,"ix":1,"mn":"ADBE Vector Group","hd":false},{"ty":"gr","it":[{"ind":0,"ty":"sh","ix":1,"ks":{"a":0,"k":{"i":[[0,91.002],[91.002,0],[0,-91.002],[-91.002,0]],"o":[[0,-91.002],[-91.002,0],[0,91.002],[91.002,0]],"v":[[164.773,0],[-0.001,-164.774],[-164.773,0],[-0.001,164.774]],"c":true},"ix":2},"nm":"パス 1","mn":"ADBE Vector Shape - Group","hd":false},{"ty":"st","c":{"a":0,"k":[0.533333333333,0.647058823529,0.85882358925,1],"ix":3},"o":{"a":0,"k":100,"ix":4},"w":{"a":0,"k":10,"ix":5},"lc":1,"lj":1,"ml":10,"bm":0,"nm":"線 1","mn":"ADBE Vector Graphic - Stroke","hd":false},{"ty":"tm","s":{"a":0,"k":0,"ix":1},"e":{"a":1,"k":[{"i":{"x":[0.556],"y":[0.816]},"o":{"x":[0.619],"y":[0.013]},"t":4,"s":[0]},{"t":34.0000013848484,"s":[100]}],"ix":2},"o":{"a":0,"k":0,"ix":3},"m":1,"ix":3,"nm":"パスのトリミング 1","mn":"ADBE Vector Filter - Trim","hd":false},{"ty":"tr","p":{"a":0,"k":[189.773,514.433],"ix":2},"a":{"a":0,"k":[0,0],"ix":1},"s":{"a":0,"k":[100,100],"ix":3},"r":{"a":0,"k":-90,"ix":6},"o":{"a":0,"k":100,"ix":7},"sk":{"a":0,"k":0,"ix":4},"sa":{"a":0,"k":0,"ix":5},"nm":"トランスフォーム"}],"nm":"グループ 2","np":3,"cix":2,"bm":0,"ix":2,"mn":"ADBE Vector Group","hd":false},{"ty":"gr","it":[{"ind":0,"ty":"sh","ix":1,"ks":{"a":0,"k":{"i":[[0,91.002],[91.002,0],[0,-91.002],[-91.002,0]],"o":[[0,-91.002],[-91.002,0],[0,91.002],[91.002,0]],"v":[[164.773,0],[0,-164.774],[-164.773,0],[0,164.774]],"c":true},"ix":2},"nm":"パス 1","mn":"ADBE Vector Shape - Group","hd":false},{"ty":"st","c":{"a":0,"k":[0.533333333333,0.647058823529,0.85882358925,1],"ix":3},"o":{"a":0,"k":100,"ix":4},"w":{"a":0,"k":10,"ix":5},"lc":1,"lj":1,"ml":10,"bm":0,"nm":"線 1","mn":"ADBE Vector Graphic - Stroke","hd":false},{"ty":"tm","s":{"a":0,"k":0,"ix":1},"e":{"a":1,"k":[{"i":{"x":[0.556],"y":[0.816]},"o":{"x":[0.619],"y":[0.013]},"t":0,"s":[0]},{"t":30.0000012219251,"s":[100]}],"ix":2},"o":{"a":0,"k":0,"ix":3},"m":1,"ix":3,"nm":"パスのトリミング 1","mn":"ADBE Vector Filter - Trim","hd":false},{"ty":"tr","p":{"a":0,"k":[450.991,189.774],"ix":2},"a":{"a":0,"k":[0,0],"ix":1},"s":{"a":0,"k":[100,100],"ix":3},"r":{"a":0,"k":-90,"ix":6},"o":{"a":0,"k":100,"ix":7},"sk":{"a":0,"k":0,"ix":4},"sa":{"a":0,"k":0,"ix":5},"nm":"トランスフォーム"}],"nm":"グループ 3","np":3,"cix":2,"bm":0,"ix":3,"mn":"ADBE Vector Group","hd":false}],"ip":0,"op":151.000006150356,"st":0,"bm":0},{"ddd":0,"ind":14,"ty":2,"nm":"09_logo.png","cl":"png","refId":"image_0","sr":1,"ks":{"o":{"a":1,"k":[{"i":{"x":[0.833],"y":[0.833]},"o":{"x":[0.167],"y":[0.167]},"t":4,"s":[0]},{"t":6.00000024438501,"s":[100]}],"ix":11},"r":{"a":0,"k":0,"ix":10},"p":{"a":0,"k":[455.178,185.506,0],"ix":2,"l":2},"a":{"a":0,"k":[658,252.5,0],"ix":1,"l":2},"s":{"a":0,"k":[10.838,10.838,100],"ix":6,"l":2}},"ao":0,"ip":0,"op":899.000036617021,"st":0,"bm":0},{"ddd":0,"ind":15,"ty":5,"nm":"user-jp","sr":1,"ks":{"o":{"a":1,"k":[{"i":{"x":[0.833],"y":[0.833]},"o":{"x":[0.167],"y":[0.167]},"t":4,"s":[0]},{"t":6.00000024438501,"s":[100]}],"ix":11},"r":{"a":0,"k":0,"ix":10},"p":{"a":0,"k":[716.362,489.559,0],"ix":2,"l":2},"a":{"a":0,"k":[0,0,0],"ix":1,"l":2},"s":{"a":0,"k":[100,100,100],"ix":6,"l":2}},"ao":0,"t":{"d":{"k":[{"s":{"s":14,"f":"NotoSansJP-Regular","t":"ユーザー","ca":0,"j":2,"tr":75,"lh":16.8000011444092,"ls":0,"fc":[0.047,0.188,0.588]},"t":0}]},"p":{},"m":{"g":1,"a":{"a":0,"k":[0,0],"ix":2}},"a":[]},"ip":0,"op":151.000006150356,"st":0,"bm":0},{"ddd":0,"ind":16,"ty":5,"nm":"user","sr":1,"ks":{"o":{"a":1,"k":[{"i":{"x":[0.833],"y":[0.833]},"o":{"x":[0.167],"y":[0.167]},"t":4,"s":[0]},{"t":6.00000024438501,"s":[100]}],"ix":11},"r":{"a":0,"k":0,"ix":10},"p":{"a":0,"k":[714.726,531.618,0],"ix":2,"l":2},"a":{"a":0,"k":[0,0,0],"ix":1,"l":2},"s":{"a":0,"k":[100,100,100],"ix":6,"l":2}},"ao":0,"t":{"d":{"k":[{"s":{"s":36,"f":"Outfit-Bold","t":"User","ca":0,"j":2,"tr":10,"lh":43.2000007629395,"ls":0,"fc":[0.047,0.188,0.588]},"t":0}]},"p":{},"m":{"g":1,"a":{"a":0,"k":[0,0],"ix":2}},"a":[]},"ip":0,"op":151.000006150356,"st":0,"bm":0},{"ddd":0,"ind":17,"ty":5,"nm":"client-jp","sr":1,"ks":{"o":{"a":1,"k":[{"i":{"x":[0.833],"y":[0.833]},"o":{"x":[0.167],"y":[0.167]},"t":4,"s":[0]},{"t":6.00000024438501,"s":[100]}],"ix":11},"r":{"a":0,"k":0,"ix":10},"p":{"a":0,"k":[191.84,489.559,0],"ix":2,"l":2},"a":{"a":0,"k":[0,0,0],"ix":1,"l":2},"s":{"a":0,"k":[100,100,100],"ix":6,"l":2}},"ao":0,"t":{"d":{"k":[{"s":{"s":14,"f":"NotoSansJP-Regular","t":"クライアント","ca":0,"j":2,"tr":75,"lh":16.8000011444092,"ls":0,"fc":[0.047,0.188,0.588]},"t":0}]},"p":{},"m":{"g":1,"a":{"a":0,"k":[0,0],"ix":2}},"a":[]},"ip":0,"op":151.000006150356,"st":0,"bm":0},{"ddd":0,"ind":18,"ty":5,"nm":"client","sr":1,"ks":{"o":{"a":1,"k":[{"i":{"x":[0.833],"y":[0.833]},"o":{"x":[0.167],"y":[0.167]},"t":4,"s":[0]},{"t":6.00000024438501,"s":[100]}],"ix":11},"r":{"a":0,"k":0,"ix":10},"p":{"a":0,"k":[190.203,531.618,0],"ix":2,"l":2},"a":{"a":0,"k":[0,0,0],"ix":1,"l":2},"s":{"a":0,"k":[100,100,100],"ix":6,"l":2}},"ao":0,"t":{"d":{"k":[{"s":{"s":36,"f":"Outfit-Bold","t":"Client","ca":0,"j":2,"tr":10,"lh":43.2000007629395,"ls":0,"fc":[0.047,0.188,0.588]},"t":0}]},"p":{},"m":{"g":1,"a":{"a":0,"k":[0,0],"ix":2}},"a":[]},"ip":0,"op":151.000006150356,"st":0,"bm":0}],"markers":[],"chars":[{"ch":"C","size":36,"style":"Bold","w":66.1,"data":{"shapes":[{"ty":"gr","it":[{"ind":0,"ty":"sh","ix":1,"ks":{"a":0,"k":{"i":[[-4.367,1.8],[-3.4,3.134],[0,0],[2.666,-1.133],[3.6,0],[2.566,1.067],[1.833,1.934],[1.033,2.734],[0,3.334],[-1.034,2.734],[-1.834,1.934],[-2.567,1.034],[-3.067,0],[-2.634,-1.133],[-1.867,-2],[0,0],[4.366,1.8],[5.6,0],[4.5,-1.833],[3.333,-3.266],[1.866,-4.433],[0,-5.133],[-1.867,-4.433],[-3.367,-3.333],[-4.5,-1.833],[-5.267,0]],"o":[[4.366,-1.8],[0,0],[-1.934,2],[-2.667,1.134],[-3.067,0],[-2.567,-1.066],[-1.834,-1.933],[-1.034,-2.733],[0,-3.266],[1.033,-2.733],[1.833,-1.933],[2.566,-1.033],[3.466,0],[2.633,1.134],[0,0],[-3.267,-3.133],[-4.367,-1.8],[-5.267,0],[-4.5,1.834],[-3.334,3.267],[-1.867,4.434],[0,5.134],[1.866,4.434],[3.366,3.334],[4.5,1.833],[5.733,0]],"v":[[55.45,-1.6],[67.1,-9],[56.5,-19.6],[49.6,-14.9],[40.2,-13.2],[31.75,-14.8],[25.15,-19.3],[20.85,-26.3],[19.3,-35.4],[20.85,-44.4],[25.15,-51.4],[31.75,-55.85],[40.2,-57.4],[49.35,-55.7],[56.1,-51],[66.6,-61.6],[55.15,-69],[40.2,-71.7],[25.55,-68.95],[13.8,-61.3],[6,-49.75],[3.2,-35.4],[6,-21.05],[13.85,-9.4],[25.65,-1.65],[40.3,1.1]],"c":true},"ix":2},"nm":"C","mn":"ADBE Vector Shape - Group","hd":false}],"nm":"C","np":3,"cix":2,"bm":0,"ix":1,"mn":"ADBE Vector Group","hd":false}]},"fFamily":"Outfit"},{"ch":"l","size":36,"style":"Bold","w":26.1,"data":{"shapes":[{"ty":"gr","it":[{"ind":0,"ty":"sh","ix":1,"ks":{"a":0,"k":{"i":[[0,0],[0,0],[0,0],[0,0]],"o":[[0,0],[0,0],[0,0],[0,0]],"v":[[20.7,0],[20.7,-72.6],[5.4,-72.6],[5.4,0]],"c":true},"ix":2},"nm":"l","mn":"ADBE Vector Shape - Group","hd":false}],"nm":"l","np":3,"cix":2,"bm":0,"ix":1,"mn":"ADBE Vector Group","hd":false}]},"fFamily":"Outfit"},{"ch":"i","size":36,"style":"Bold","w":26.1,"data":{"shapes":[{"ty":"gr","it":[{"ind":0,"ty":"sh","ix":1,"ks":{"a":0,"k":{"i":[[0,0],[0,0],[0,0],[0,0]],"o":[[0,0],[0,0],[0,0],[0,0]],"v":[[20.7,0],[20.7,-48.6],[5.4,-48.6],[5.4,0]],"c":true},"ix":2},"nm":"i","mn":"ADBE Vector Shape - Group","hd":false},{"ind":1,"ty":"sh","ix":2,"ks":{"a":0,"k":{"i":[[-1.534,1.634],[0,2.334],[1.533,1.6],[2.4,0],[1.566,-1.6],[0,-2.4],[-1.567,-1.633],[-2.4,0]],"o":[[1.533,-1.633],[0,-2.4],[-1.534,-1.6],[-2.4,0],[-1.567,1.6],[0,2.334],[1.566,1.634],[2.4,0]],"v":[[19,-57.75],[21.3,-63.7],[19,-69.7],[13.1,-72.1],[7.15,-69.7],[4.8,-63.7],[7.15,-57.75],[13.1,-55.3]],"c":true},"ix":2},"nm":"i","mn":"ADBE Vector Shape - Group","hd":false}],"nm":"i","np":5,"cix":2,"bm":0,"ix":1,"mn":"ADBE Vector Group","hd":false}]},"fFamily":"Outfit"},{"ch":"e","size":36,"style":"Bold","w":54.8,"data":{"shapes":[{"ty":"gr","it":[{"ind":0,"ty":"sh","ix":1,"ks":{"a":0,"k":{"i":[[-3.4,1.4],[-2.4,2.8],[0,0],[1.933,-0.833],[2.4,0],[1.9,1.1],[1.033,2.034],[0,2.867],[-0.967,2],[-1.767,1.1],[-2.4,0],[-1.567,-0.966],[-0.8,-1.833],[-0.067,-2.8],[0,0],[0,0],[0,0],[0,0],[-0.1,0.967],[0,0.867],[2.1,3.667],[3.666,2.067],[4.8,0],[3.933,-2.2],[2.3,-3.833],[0,-4.866],[-2.334,-3.866],[-4.1,-2.166],[-5.267,0]],"o":[[3.4,-1.4],[0,0],[-1.467,1.667],[-1.934,0.834],[-2.6,0],[-1.9,-1.1],[-1.034,-2.033],[0,-2.866],[0.966,-2],[1.766,-1.1],[2.266,0],[1.566,0.967],[0.8,1.834],[0,0],[0,0],[0,0],[0,0],[0.266,-1.266],[0.1,-0.966],[0,-4.733],[-2.1,-3.666],[-3.667,-2.066],[-4.934,0],[-3.934,2.2],[-2.3,3.834],[0,4.867],[2.333,3.867],[4.1,2.166],[4.066,0]],"v":[[40.6,-1],[49.3,-7.3],[40.9,-15.7],[35.8,-11.95],[29.3,-10.7],[22.55,-12.35],[18.15,-17.05],[16.6,-24.4],[18.05,-31.7],[22.15,-36.35],[28.4,-38],[34.15,-36.55],[37.7,-32.35],[39,-25.4],[45.6,-29.8],[10.2,-29.7],[10.2,-19.2],[52.1,-19.3],[52.65,-22.65],[52.8,-25.4],[49.65,-38],[41,-46.6],[28.3,-49.7],[15,-46.4],[5.65,-37.35],[2.2,-24.3],[5.7,-11.2],[15.35,-2.15],[29.4,1.1]],"c":true},"ix":2},"nm":"e","mn":"ADBE Vector Shape - Group","hd":false}],"nm":"e","np":3,"cix":2,"bm":0,"ix":1,"mn":"ADBE Vector Group","hd":false}]},"fFamily":"Outfit"},{"ch":"n","size":36,"style":"Bold","w":57.2,"data":{"shapes":[{"ty":"gr","it":[{"ind":0,"ty":"sh","ix":1,"ks":{"a":0,"k":{"i":[[0,0],[0,0],[1.6,2.8],[2.766,1.7],[3.6,0],[2.966,-1.566],[1.666,-2.866],[0,-3.8],[0,0],[-0.734,1.3],[-1.267,0.7],[-1.667,0],[-1.567,-1.566],[0,-2.533],[0,0]],"o":[[0,0],[0,-3.333],[-1.6,-2.8],[-2.767,-1.7],[-3.734,0],[-2.967,1.567],[-1.667,2.867],[0,0],[0,-1.666],[0.733,-1.3],[1.266,-0.7],[2.4,0],[1.566,1.567],[0,0],[0,0]],"v":[[52.8,0],[52.8,-31.1],[50.4,-40.3],[43.85,-47.05],[34.3,-49.6],[24.25,-47.25],[17.3,-40.6],[14.8,-30.6],[20.7,-27.7],[21.8,-32.15],[24.8,-35.15],[29.2,-36.2],[35.15,-33.85],[37.5,-27.7],[37.5,0]],"c":true},"ix":2},"nm":"n","mn":"ADBE Vector Shape - Group","hd":false},{"ind":1,"ty":"sh","ix":2,"ks":{"a":0,"k":{"i":[[0,0],[0,0],[0,0],[0,0]],"o":[[0,0],[0,0],[0,0],[0,0]],"v":[[20.7,0],[20.7,-48.6],[5.4,-48.6],[5.4,0]],"c":true},"ix":2},"nm":"n","mn":"ADBE Vector Shape - Group","hd":false}],"nm":"n","np":5,"cix":2,"bm":0,"ix":1,"mn":"ADBE Vector Group","hd":false}]},"fFamily":"Outfit"},{"ch":"t","size":36,"style":"Bold","w":38.7,"data":{"shapes":[{"ty":"gr","it":[{"ind":0,"ty":"sh","ix":1,"ks":{"a":0,"k":{"i":[[0,0],[0,0],[0,0],[0,0]],"o":[[0,0],[0,0],[0,0],[0,0]],"v":[[27.6,0],[27.6,-68.7],[12.3,-68.7],[12.3,0]],"c":true},"ix":2},"nm":"t","mn":"ADBE Vector Shape - Group","hd":false},{"ind":1,"ty":"sh","ix":2,"ks":{"a":0,"k":{"i":[[0,0],[0,0],[0,0],[0,0]],"o":[[0,0],[0,0],[0,0],[0,0]],"v":[[38.6,-35.6],[38.6,-48.6],[1.3,-48.6],[1.3,-35.6]],"c":true},"ix":2},"nm":"t","mn":"ADBE Vector Shape - Group","hd":false}],"nm":"t","np":5,"cix":2,"bm":0,"ix":1,"mn":"ADBE Vector Group","hd":false}]},"fFamily":"Outfit"},{"ch":"ク","size":14,"style":"Regular","w":85.8,"data":{"shapes":[{"ty":"gr","it":[{"ind":0,"ty":"sh","ix":1,"ks":{"a":0,"k":{"i":[[-1.712,2.618],[0,0],[1.007,-1.712],[17.322,-10.373],[0,0],[-6.143,8.459],[0,0],[7.855,-9.265],[18.43,-5.438],[0,0],[-9.164,11.179],[-2.719,10.172],[-0.806,1.41],[0,0],[2.719,0],[0,0],[-0.705,1.41]],"o":[[0,0],[-0.604,2.618],[-4.33,9.064],[0,0],[10.977,-7.352],[0,0],[-2.115,9.164],[-9.164,10.675],[0,0],[18.933,-6.949],[8.963,-10.876],[0.504,-1.611],[0,0],[-1.611,0.705],[0,0],[0.906,-1.41],[0.906,-1.913]],"v":[[51.18,-78.25],[41.814,-81.271],[38.692,-73.315],[7.07,-39.276],[14.019,-34.039],[39.599,-58.813],[73.638,-58.813],[57.525,-27.393],[17.342,-2.115],[24.593,4.431],[64.675,-22.961],[82.601,-57.605],[84.917,-62.943],[78.17,-67.072],[71.624,-66.064],[44.332,-66.064],[46.749,-70.294]],"c":true},"ix":2},"nm":"ク","mn":"ADBE Vector Shape - Group","hd":false}],"nm":"ク","np":3,"cix":2,"bm":0,"ix":1,"mn":"ADBE Vector Group","hd":false}]},"fFamily":"Noto Sans JP"},{"ch":"ラ","size":14,"style":"Regular","w":86.5,"data":{"shapes":[{"ty":"gr","it":[{"ind":0,"ty":"sh","ix":1,"ks":{"a":0,"k":{"i":[[2.618,0.403],[0,0],[-3.122,0],[0,0],[-2.417,-0.201],[0,0],[3.223,0],[0,0]],"o":[[0,0],[2.719,-0.201],[0,0],[3.424,0],[0,0],[-2.417,0.403],[0,0],[-3.223,0]],"v":[[15.964,-75.027],[15.964,-66.669],[25.027,-66.971],[64.505,-66.971],[73.77,-66.669],[73.77,-75.027],[64.606,-74.524],[25.027,-74.524]],"c":true},"ix":2},"nm":"ラ","mn":"ADBE Vector Shape - Group","hd":false},{"ind":1,"ty":"sh","ix":2,"ks":{"a":0,"k":{"i":[[-0.504,0.906],[0,0],[2.316,0],[0,0],[3.726,0.403],[0,0],[-2.417,0],[0,0],[6.143,-6.445],[14.301,-2.921],[0,0],[-10.574,11.581],[-2.719,9.97]],"o":[[0,0],[-1.108,0.604],[0,0],[-2.719,0],[0,0],[3.625,-0.201],[0,0],[-1.813,7.251],[-8.56,9.064],[0,0],[12.891,-3.525],[7.452,-8.157],[0.201,-0.705]],"v":[[81.122,-48.441],[75.381,-52.066],[69.842,-51.26],[16.769,-51.26],[6.9,-51.865],[6.9,-43.405],[16.769,-43.707],[70.245,-43.707],[58.261,-21.451],[22.812,-3.021],[29.056,4.129],[65.109,-16.919],[79.812,-45.52]],"c":true},"ix":2},"nm":"ラ","mn":"ADBE Vector Shape - Group","hd":false}],"nm":"ラ","np":5,"cix":2,"bm":0,"ix":1,"mn":"ADBE Vector Group","hd":false}]},"fFamily":"Noto Sans JP"},{"ch":"イ","size":14,"style":"Regular","w":88.1,"data":{"shapes":[{"ty":"gr","it":[{"ind":0,"ty":"sh","ix":1,"ks":{"a":0,"k":{"i":[[17.422,-4.733],[0,0],[-10.574,6.042],[0,0],[0.302,-1.913],[0,0],[0,3.827],[0,0],[-7.654,7.956],[0,0],[10.474,-6.546]],"o":[[0,0],[13.998,-4.33],[0,0],[0,3.827],[0,0],[-0.403,-2.014],[0,0],[10.272,-6.848],[0,0],[-6.949,8.359],[-11.179,7.05]],"v":[[4.961,-36.356],[8.989,-28.5],[47.359,-44.916],[47.359,-7.654],[46.755,3.122],[56.624,3.122],[56.02,-7.654],[56.02,-50.153],[83.211,-72.61],[76.464,-78.854],[48.97,-55.188]],"c":true},"ix":2},"nm":"イ","mn":"ADBE Vector Shape - Group","hd":false}],"nm":"イ","np":3,"cix":2,"bm":0,"ix":1,"mn":"ADBE Vector Group","hd":false}]},"fFamily":"Noto Sans JP"},{"ch":"ア","size":14,"style":"Regular","w":93.1,"data":{"shapes":[{"ty":"gr","it":[{"ind":0,"ty":"sh","ix":1,"ks":{"a":0,"k":{"i":[[-0.705,1.007],[0,0],[1.913,0],[0,0],[3.525,0.504],[0,0],[-3.726,0],[0,0],[9.265,-5.338],[0,0],[-4.028,6.848]],"o":[[0,0],[-1.511,0.302],[0,0],[-3.726,0],[0,0],[3.928,-0.403],[0,0],[-3.323,6.244],[0,0],[11.481,-7.956],[0.705,-1.108]],"v":[[90.159,-68.079],[85.224,-72.812],[78.175,-72.208],[20.368,-72.208],[8.888,-73.114],[8.888,-63.95],[20.368,-64.554],[77.772,-64.554],[55.717,-41.995],[62.364,-36.658],[87.44,-64.453]],"c":true},"ix":2},"nm":"ア","mn":"ADBE Vector Shape - Group","hd":false},{"ind":1,"ty":"sh","ix":2,"ks":{"a":0,"k":{"i":[[0,27.292],[0,0],[0,-2.417],[15.61,-9.567],[2.82,-0.906],[0,0]],"o":[[0,0],[0.302,2.618],[0,16.818],[-2.82,2.014],[0,0],[25.681,-12.79]],"v":[[49.977,-54.785],[40.913,-54.785],[41.316,-47.534],[23.49,-6.848],[14.427,-2.316],[21.879,3.726]],"c":true},"ix":2},"nm":"ア","mn":"ADBE Vector Shape - Group","hd":false}],"nm":"ア","np":5,"cix":2,"bm":0,"ix":1,"mn":"ADBE Vector Group","hd":false}]},"fFamily":"Noto Sans JP"},{"ch":"ン","size":14,"style":"Regular","w":88.8,"data":{"shapes":[{"ty":"gr","it":[{"ind":0,"ty":"sh","ix":1,"ks":{"a":0,"k":{"i":[[7.15,4.733],[0,0],[-5.035,-5.237],[0,0]],"o":[[0,0],[7.452,5.035],[0,0],[-5.64,-5.64]],"v":[[17.261,-73.819],[11.52,-67.676],[36.597,-46.628],[42.941,-52.972]],"c":true},"ix":2},"nm":"ン","mn":"ADBE Vector Shape - Group","hd":false},{"ind":1,"ty":"sh","ix":2,"ks":{"a":0,"k":{"i":[[17.624,-2.618],[0,0],[-10.071,6.345],[-6.848,12.589],[0,0],[15.509,-9.769]],"o":[[0,0],[16.818,-3.122],[15.207,-9.567],[0,0],[-5.841,12.387],[-9.567,5.942]],"v":[[8.6,-6.345],[13.937,1.913],[53.516,-13.696],[87.354,-49.548],[82.52,-58.109],[48.883,-21.048]],"c":true},"ix":2},"nm":"ン","mn":"ADBE Vector Shape - Group","hd":false}],"nm":"ン","np":5,"cix":2,"bm":0,"ix":1,"mn":"ADBE Vector Group","hd":false}]},"fFamily":"Noto Sans JP"},{"ch":"ト","size":14,"style":"Regular","w":77,"data":{"shapes":[{"ty":"gr","it":[{"ind":0,"ty":"sh","ix":1,"ks":{"a":0,"k":{"i":[[0,0],[0.504,-3.223],[0,0],[0,3.122],[0.101,15.106],[-10.977,-5.942],[0,0],[13.293,4.028],[0,4.23],[-0.302,3.122],[0,0],[0,-2.82]],"o":[[0,3.726],[0,0],[-0.403,-3.323],[0,-2.921],[11.179,3.525],[0,0],[-10.574,-5.338],[0,-6.345],[0,-3.021],[0,0],[0.604,3.122],[0,0]],"v":[[19.039,-8.862],[18.334,3.021],[28.102,3.021],[27.498,-8.862],[27.397,-42.096],[66.976,-25.882],[70.4,-34.442],[27.397,-51.059],[27.397,-67.474],[28.102,-77.948],[18.233,-77.948],[19.039,-67.474]],"c":true},"ix":2},"nm":"ト","mn":"ADBE Vector Shape - Group","hd":false}],"nm":"ト","np":3,"cix":2,"bm":0,"ix":1,"mn":"ADBE Vector Group","hd":false}]},"fFamily":"Noto Sans JP"},{"ch":"U","size":36,"style":"Bold","w":70.2,"data":{"shapes":[{"ty":"gr","it":[{"ind":0,"ty":"sh","ix":1,"ks":{"a":0,"k":{"i":[[-4.4,2.467],[-2.467,4.334],[0,5.6],[0,0],[0,0],[0,0],[1.166,-2.033],[2,-1.1],[2.666,0],[2.1,1.1],[1.2,2.067],[0,2.8],[0,0],[0,0],[0,0],[-2.5,-4.366],[-4.434,-2.466],[-5.8,0]],"o":[[4.4,-2.466],[2.466,-4.333],[0,0],[0,0],[0,0],[0,2.8],[-1.167,2.034],[-2,1.1],[-2.534,0],[-2.1,-1.1],[-1.2,-2.066],[0,0],[0,0],[0,0],[0,5.6],[2.5,4.367],[4.433,2.467],[5.8,0]],"v":[[50.5,-2.6],[60.8,-12.8],[64.5,-27.7],[64.5,-70.6],[48.7,-70.6],[48.7,-26.8],[46.95,-19.55],[42.2,-14.85],[35.2,-13.2],[28.25,-14.85],[23.3,-19.6],[21.5,-26.9],[21.5,-70.6],[5.7,-70.6],[5.7,-27.8],[9.45,-12.85],[19.85,-2.6],[35.2,1.1]],"c":true},"ix":2},"nm":"U","mn":"ADBE Vector Shape - Group","hd":false}],"nm":"U","np":3,"cix":2,"bm":0,"ix":1,"mn":"ADBE Vector Group","hd":false}]},"fFamily":"Outfit"},{"ch":"s","size":36,"style":"Bold","w":45.8,"data":{"shapes":[{"ty":"gr","it":[{"ind":0,"ty":"sh","ix":1,"ks":{"a":0,"k":{"i":[[-3.567,2.8],[0,4.734],[1.133,1.9],[1.8,1.134],[2,0.667],[1.8,0.467],[1.133,0.6],[0,1],[-0.867,0.5],[-1.734,0],[-1.9,-0.733],[-1.534,-1.8],[0,0],[3.5,1.434],[4.133,0],[2.933,-1.333],[1.6,-2.3],[0,-3.133],[-1.134,-1.9],[-1.8,-1.066],[-2,-0.6],[-1.8,-0.5],[-1.167,-0.633],[0,-1.2],[0.966,-0.533],[1.8,0],[2.2,0.967],[1.6,1.734],[0,0],[-2.367,-1.366],[-2.767,-0.733],[-2.867,0]],"o":[[3.566,-2.8],[0,-3.066],[-1.134,-1.9],[-1.8,-1.133],[-2,-0.666],[-1.8,-0.466],[-1.134,-0.6],[0,-0.933],[0.866,-0.5],[1.8,0],[1.9,0.734],[0,0],[-2.2,-2.8],[-3.5,-1.433],[-3.934,0],[-2.934,1.334],[-1.6,2.3],[0,2.934],[1.133,1.9],[1.8,1.067],[2,0.6],[1.8,0.5],[1.166,0.634],[0,0.934],[-0.967,0.534],[-2.6,0],[-2.2,-0.966],[0,0],[1.666,1.8],[2.366,1.367],[2.766,0.733],[6.066,0]],"v":[[37.55,-3],[42.9,-14.3],[41.2,-21.75],[36.8,-26.3],[31.1,-29],[25.4,-30.7],[21,-32.3],[19.3,-34.7],[20.6,-36.85],[24.5,-37.6],[30.05,-36.5],[35.2,-32.7],[43.9,-41.5],[35.35,-47.85],[23.9,-50],[13.6,-48],[6.8,-42.55],[4.4,-34.4],[6.1,-27.15],[10.5,-22.7],[16.2,-20.2],[21.9,-18.55],[26.35,-16.85],[28.1,-14.1],[26.65,-11.9],[22.5,-11.1],[15.3,-12.55],[9.6,-16.6],[0.9,-7.8],[6.95,-3.05],[14.65,0.1],[23.1,1.2]],"c":true},"ix":2},"nm":"s","mn":"ADBE Vector Shape - Group","hd":false}],"nm":"s","np":3,"cix":2,"bm":0,"ix":1,"mn":"ADBE Vector Group","hd":false}]},"fFamily":"Outfit"},{"ch":"r","size":36,"style":"Bold","w":42.3,"data":{"shapes":[{"ty":"gr","it":[{"ind":0,"ty":"sh","ix":1,"ks":{"a":0,"k":{"i":[[0,0],[0,0],[0,0],[0,0]],"o":[[0,0],[0,0],[0,0],[0,0]],"v":[[20.7,0],[20.7,-48.6],[5.4,-48.6],[5.4,0]],"c":true},"ix":2},"nm":"r","mn":"ADBE Vector Shape - Group","hd":false},{"ind":1,"ty":"sh","ix":2,"ks":{"a":0,"k":{"i":[[-1.5,1.567],[-2.534,0],[-1,-0.4],[-0.667,-0.733],[0,0],[1.766,0.7],[2.333,0],[3,-3.133],[1.266,-5.666],[0,0]],"o":[[1.5,-1.566],[1.266,0],[1,0.4],[0,0],[-1.334,-1.466],[-1.767,-0.7],[-5.334,0],[-3,3.134],[0,0],[0,-3.133]],"v":[[22.95,-33.75],[29,-36.1],[32.4,-35.5],[34.9,-33.8],[44,-45.3],[39.35,-48.55],[33.2,-49.6],[20.7,-44.9],[14.3,-31.7],[20.7,-26.7]],"c":true},"ix":2},"nm":"r","mn":"ADBE Vector Shape - Group","hd":false}],"nm":"r","np":5,"cix":2,"bm":0,"ix":1,"mn":"ADBE Vector Group","hd":false}]},"fFamily":"Outfit"},{"ch":"ユ","size":14,"style":"Regular","w":97.6,"data":{"shapes":[{"ty":"gr","it":[{"ind":0,"ty":"sh","ix":1,"ks":{"a":0,"k":{"i":[[-0.403,1.007],[0,0],[2.014,0],[0,0],[3.021,0.403],[0,0],[-3.726,0],[0,0],[1.813,-10.776],[0,0],[3.021,0.403],[0,0],[-2.82,0],[0,0],[-2.618,-0.302],[0,0],[3.021,0],[0,0],[-1.108,9.467]],"o":[[0,0],[-1.208,0.504],[0,0],[-3.323,0],[0,0],[3.223,-0.201],[0,0],[-0.302,7.05],[0,0],[-2.82,0],[0,0],[3.122,-0.302],[0,0],[2.014,0],[0,0],[-2.518,0.302],[0,0],[1.712,-10.776],[0.101,-0.806]],"v":[[77.555,-64.755],[70.808,-67.978],[64.564,-67.072],[27.402,-67.072],[17.835,-67.676],[17.835,-58.713],[27.503,-59.116],[67.182,-59.116],[60.838,-14.301],[15.418,-14.301],[6.556,-14.905],[6.556,-5.74],[15.418,-6.143],[83.396,-6.143],[91.755,-5.74],[91.755,-14.905],[83.396,-14.301],[69.7,-14.301],[76.749,-61.432]],"c":true},"ix":2},"nm":"ユ","mn":"ADBE Vector Shape - Group","hd":false}],"nm":"ユ","np":3,"cix":2,"bm":0,"ix":1,"mn":"ADBE Vector Group","hd":false}]},"fFamily":"Noto Sans JP"},{"ch":"ー","size":14,"style":"Regular","w":98.5,"data":{"shapes":[{"ty":"gr","it":[{"ind":0,"ty":"sh","ix":1,"ks":{"a":0,"k":{"i":[[3.021,0.201],[0,0],[-5.539,0],[0,0],[-2.014,-0.101],[0,0],[5.035,0],[0,0]],"o":[[0,0],[3.122,-0.302],[0,0],[4.532,0],[0,0],[-2.216,0.201],[0,0],[-5.64,0]],"v":[[9.572,-43.607],[9.572,-33.737],[23.571,-34.241],[78.859,-34.241],[89.635,-33.737],[89.635,-43.607],[78.759,-43.103],[23.571,-43.103]],"c":true},"ix":2},"nm":"ー","mn":"ADBE Vector Shape - Group","hd":false}],"nm":"ー","np":3,"cix":2,"bm":0,"ix":1,"mn":"ADBE Vector Group","hd":false}]},"fFamily":"Noto Sans JP"},{"ch":"ザ","size":14,"style":"Regular","w":96,"data":{"shapes":[{"ty":"gr","it":[{"ind":0,"ty":"sh","ix":1,"ks":{"a":0,"k":{"i":[[1.813,3.625],[0,0],[-1.511,-4.33],[0,0]],"o":[[0,0],[1.913,3.827],[0,0],[-1.309,-4.129]],"v":[[79.864,-76.84],[75.03,-75.33],[80.771,-61.13],[85.705,-62.842]],"c":true},"ix":2},"nm":"ザ","mn":"ADBE Vector Shape - Group","hd":false},{"ind":1,"ty":"sh","ix":2,"ks":{"a":0,"k":{"i":[[1.913,3.625],[0,0],[-1.611,-4.431],[0,0]],"o":[[0,0],[2.014,3.726],[0,0],[-1.41,-4.129]],"v":[[89.834,-79.861],[85,-78.351],[90.942,-64.352],[95.877,-65.964]],"c":true},"ix":2},"nm":"ザ","mn":"ADBE Vector Shape - Group","hd":false},{"ind":2,"ty":"sh","ix":3,"ks":{"a":0,"k":{"i":[[0,26.788],[0,0],[0,0],[-1.108,-0.101],[0,0],[4.532,0],[0,0],[0,0],[-0.101,1.007],[0,0],[0,-4.028],[0,0],[0,0],[0,0],[-0.101,0.906],[0,0],[0,-2.216],[0,0],[0,0],[0.906,0.201],[0,0],[-4.431,0],[0,0],[0,0],[0.101,-0.906],[0,0],[0,3.726],[0,0],[0,0],[0,0],[18.329,-6.949],[0,0]],"o":[[0,0],[0,0],[4.431,0],[0,0],[-1.41,0.302],[0,0],[0,0],[0,-4.028],[0,0],[0.101,0.906],[0,0],[0,0],[0,0],[0,-3.424],[0,0],[0.302,2.316],[0,0],[0,0],[-4.23,0],[0,0],[1.108,-0.101],[0,0],[0,0],[0,3.827],[0,0],[-0.101,-0.906],[0,0],[0,0],[0,0],[0,28.198],[0,0],[22.961,-10.272]],"v":[[70.297,-44.513],[70.297,-48.038],[81.375,-48.038],[90.539,-47.736],[90.539,-56.296],[81.274,-55.692],[70.297,-55.692],[70.297,-68.28],[70.801,-76.538],[61.737,-76.538],[62.14,-68.28],[62.14,-55.692],[33.539,-55.692],[33.539,-68.683],[33.941,-75.934],[24.978,-75.934],[25.482,-68.582],[25.482,-55.692],[14.605,-55.692],[4.535,-56.396],[4.535,-47.635],[14.605,-48.038],[25.482,-48.038],[25.482,-31.723],[24.978,-22.659],[33.941,-22.659],[33.539,-31.723],[33.539,-48.038],[62.14,-48.038],[62.14,-43.808],[34.747,0],[41.495,6.445]],"c":true},"ix":2},"nm":"ザ","mn":"ADBE Vector Shape - Group","hd":false}],"nm":"ザ","np":6,"cix":2,"bm":0,"ix":1,"mn":"ADBE Vector Group","hd":false}]},"fFamily":"Noto Sans JP"},{"ch":"サ","size":16,"style":"Bold","w":95.6,"data":{"shapes":[{"ty":"gr","it":[{"ind":0,"ty":"sh","ix":1,"ks":{"a":0,"k":{"i":[[0,24.976],[0,0],[0,0],[-2.216,-0.201],[0,0],[5.338,0],[0,0],[0,0],[-0.302,2.014],[0,0],[0,-4.028],[0,0],[0,0],[0,0],[-0.302,1.913],[0,0],[0,-2.921],[0,0],[0,0],[1.712,0.302],[0,0],[-5.035,0],[0,0],[0,0],[0.302,-2.014],[0,0],[0,4.431],[0,0],[0,0],[0,0],[19.437,-6.747],[0,0]],"o":[[0,0],[0,0],[5.338,0],[0,0],[-2.719,0.504],[0,0],[0,0],[0,-4.028],[0,0],[0.302,2.014],[0,0],[0,0],[0,0],[0,-3.928],[0,0],[0.302,3.021],[0,0],[0,0],[-5.035,0],[0,0],[2.216,-0.201],[0,0],[0,0],[0,4.532],[0,0],[-0.101,-2.014],[0,0],[0,0],[0,0],[0,24.774],[0,0],[24.271,-10.675]],"v":[[74.53,-44.513],[74.53,-47.836],[81.982,-47.836],[93.06,-47.534],[93.06,-60.928],[81.982,-60.223],[74.53,-60.223],[74.53,-70.798],[75.235,-80.164],[60.833,-80.164],[61.438,-70.798],[61.438,-60.223],[37.57,-60.223],[37.57,-70.193],[38.174,-79.257],[23.873,-79.257],[24.478,-70.193],[24.478,-60.223],[15.918,-60.223],[5.041,-61.13],[5.041,-47.433],[15.918,-47.836],[24.478,-47.836],[24.478,-34.14],[23.873,-23.566],[37.973,-23.566],[37.57,-34.14],[37.57,-47.836],[61.438,-47.836],[61.438,-44.009],[33.441,-3.827],[44.216,6.345]],"c":true},"ix":2},"nm":"サ","mn":"ADBE Vector Shape - Group","hd":false}],"nm":"サ","np":3,"cix":2,"bm":0,"ix":1,"mn":"ADBE Vector Group","hd":false}]},"fFamily":"Noto Sans JP"},{"ch":"ー","size":16,"style":"Bold","w":96.7,"data":{"shapes":[{"ty":"gr","it":[{"ind":0,"ty":"sh","ix":1,"ks":{"a":0,"k":{"i":[[3.625,0.302],[0,0],[-5.74,0],[0,0],[-2.417,-0.101],[0,0],[4.733,0],[0,0]],"o":[[0,0],[3.726,-0.302],[0,0],[4.23,0],[0,0],[-2.618,0.201],[0,0],[-5.237,0]],"v":[[7.665,-46.628],[7.665,-30.817],[23.879,-31.32],[77.959,-31.32],[89.742,-30.817],[89.742,-46.628],[77.959,-46.024],[23.879,-46.024]],"c":true},"ix":2},"nm":"ー","mn":"ADBE Vector Shape - Group","hd":false}],"nm":"ー","np":3,"cix":2,"bm":0,"ix":1,"mn":"ADBE Vector Group","hd":false}]},"fFamily":"Noto Sans JP"},{"ch":"ビ","size":16,"style":"Bold","w":91.3,"data":{"shapes":[{"ty":"gr","it":[{"ind":0,"ty":"sh","ix":1,"ks":{"a":0,"k":{"i":[[2.518,3.726],[0,0],[-2.014,-4.129],[0,0]],"o":[[0,0],[2.719,3.928],[0,0],[-1.913,-3.726]],"v":[[72.223,-81.573],[64.267,-78.351],[72.122,-64.352],[80.279,-67.776]],"c":true},"ix":2},"nm":"ビ","mn":"ADBE Vector Shape - Group","hd":false},{"ind":1,"ty":"sh","ix":2,"ks":{"a":0,"k":{"i":[[2.719,3.726],[0,0],[-2.115,-4.23],[0,0]],"o":[[0,0],[2.82,3.827],[0,0],[-1.712,-3.525]],"v":[[84.106,-86.105],[76.15,-82.883],[84.307,-68.985],[92.263,-72.409]],"c":true},"ix":2},"nm":"ビ","mn":"ADBE Vector Shape - Group","hd":false},{"ind":2,"ty":"sh","ix":3,"ks":{"a":0,"k":{"i":[[-0.504,3.021],[0,0],[0,-2.216],[0,0],[-8.762,-1.611],[-6.546,0],[-9.467,1.41],[0,0],[10.474,0],[3.021,0.403],[0,4.33],[0,0],[-10.172,4.028],[-3.928,1.611],[0,0],[3.625,-1.41],[11.884,-2.921],[0,0]],"o":[[0,0],[0.504,3.021],[0,0],[0,8.661],[4.33,0.705],[11.078,0],[0,0],[-8.258,2.216],[-4.532,0],[-4.532,-0.906],[0,0],[13.092,-3.223],[3.323,-1.208],[0,0],[-3.928,2.417],[-8.963,3.827],[0,0],[0,-2.82]],"v":[[28.817,-77.243],[13.913,-77.243],[14.718,-66.769],[14.718,-11.884],[28.515,3.223],[45.434,4.33],[81.286,2.216],[81.286,-12.488],[46.24,-8.963],[34.558,-9.567],[28.012,-15.912],[28.012,-34.543],[67.489,-46.829],[79.272,-51.562],[73.834,-64.352],[62.857,-58.914],[28.012,-47.736],[28.012,-66.769]],"c":true},"ix":2},"nm":"ビ","mn":"ADBE Vector Shape - Group","hd":false}],"nm":"ビ","np":6,"cix":2,"bm":0,"ix":1,"mn":"ADBE Vector Group","hd":false}]},"fFamily":"Noto Sans JP"},{"ch":"ス","size":16,"style":"Bold","w":94.1,"data":{"shapes":[{"ty":"gr","it":[{"ind":0,"ty":"sh","ix":1,"ks":{"a":0,"k":{"i":[[-0.806,1.108],[0,0],[4.33,0],[0,0],[2.719,0.403],[0,0],[-4.23,0],[0,0],[6.647,-7.553],[16.214,-6.042],[0,0],[-10.675,11.279],[-6.546,-9.064],[0,0],[9.97,8.661],[-3.424,7.855]],"o":[[0,0],[-2.014,0.705],[0,0],[-3.021,0],[0,0],[2.115,-0.101],[0,0],[-2.216,7.15],[-9.467,10.574],[0,0],[13.797,-6.546],[9.467,9.164],[0,0],[-5.942,-7.251],[6.747,-9.064],[0.906,-2.014]],"v":[[79.69,-68.28],[71.432,-74.423],[61.059,-73.114],[25.51,-73.114],[13.626,-73.819],[13.626,-59.518],[25.51,-60.223],[59.65,-60.223],[44.644,-35.55],[3.354,-6.647],[13.727,4.23],[51.593,-24.069],[76.971,4.431],[88.452,-5.539],[60.355,-34.341],[76.166,-62.036]],"c":true},"ix":2},"nm":"ス","mn":"ADBE Vector Shape - Group","hd":false}],"nm":"ス","np":3,"cix":2,"bm":0,"ix":1,"mn":"ADBE Vector Group","hd":false}]},"fFamily":"Noto Sans JP"},{"ch":"利","size":16,"style":"Bold","w":100,"data":{"shapes":[{"ty":"gr","it":[{"ind":0,"ty":"sh","ix":1,"ks":{"a":0,"k":{"i":[[0,0],[0,0],[0,0],[0,0],[0,0],[-5.035,2.014],[0,0],[14.502,-2.115],[-0.504,-2.618],[-5.74,1.108],[0,0],[0,0],[0,0],[0,0],[7.251,-7.05],[-1.208,-3.525],[-4.532,9.164],[0,0],[0,0],[0,0],[-2.417,-3.122],[0,0],[4.935,3.726]],"o":[[0,0],[0,0],[0,0],[0,0],[6.143,-1.511],[0,0],[-9.769,4.431],[1.41,2.518],[5.438,-0.705],[0,0],[0,0],[0,0],[0,0],[-4.532,10.474],[1.913,3.021],[5.539,-5.841],[0,0],[0,0],[0,0],[4.028,4.129],[0,0],[-2.719,-2.115],[0,0]],"v":[[35.449,-44.513],[52.771,-44.513],[52.771,-55.49],[35.449,-55.49],[35.449,-70.496],[52.469,-75.732],[44.009,-84.998],[3.525,-74.625],[6.949,-65.259],[23.868,-67.978],[23.868,-55.49],[4.733,-55.49],[4.733,-44.513],[21.552,-44.513],[2.417,-15.509],[8.459,-3.827],[23.868,-27.493],[23.868,8.56],[35.449,8.56],[35.449,-26.184],[46.124,-14.401],[53.073,-24.673],[35.449,-39.075]],"c":true},"ix":2},"nm":"利","mn":"ADBE Vector Shape - Group","hd":false},{"ind":1,"ty":"sh","ix":2,"ks":{"a":0,"k":{"i":[[0,0],[0,0],[0,0],[0,0]],"o":[[0,0],[0,0],[0,0],[0,0]],"v":[[69.186,-73.114],[57.504,-73.114],[57.504,-16.818],[69.186,-16.818]],"c":true},"ix":2},"nm":"利","mn":"ADBE Vector Shape - Group","hd":false},{"ind":2,"ty":"sh","ix":3,"ks":{"a":0,"k":{"i":[[0,0],[0,0],[1.913,-0.101],[6.546,0.302],[-0.504,-3.424],[-4.129,2.014],[0,6.949],[0,0]],"o":[[0,0],[0,1.813],[-2.115,0],[1.813,3.424],[9.164,0.101],[4.129,-1.913],[0,0],[0,0]],"v":[[81.271,-83.386],[81.271,-5.942],[78.552,-3.424],[63.446,-3.726],[67.575,8.661],[87.616,6.345],[93.155,-5.841],[93.155,-83.386]],"c":true},"ix":2},"nm":"利","mn":"ADBE Vector Shape - Group","hd":false}],"nm":"利","np":6,"cix":2,"bm":0,"ix":1,"mn":"ADBE Vector Group","hd":false}]},"fFamily":"Noto Sans JP"},{"ch":"用","size":16,"style":"Bold","w":100,"data":{"shapes":[{"ty":"gr","it":[{"ind":0,"ty":"sh","ix":1,"ks":{"a":0,"k":{"i":[[0,0],[0,0],[0,0],[0,0]],"o":[[0,0],[0,0],[0,0],[0,0]],"v":[[57.404,-31.924],[57.404,-44.312],[78.653,-44.312],[78.653,-31.924]],"c":true},"ix":2},"nm":"用","mn":"ADBE Vector Shape - Group","hd":false},{"ind":1,"ty":"sh","ix":2,"ks":{"a":0,"k":{"i":[[0,0],[0,3.223],[0,0],[0,0],[0,0]],"o":[[0.201,-3.726],[0,0],[0,0],[0,0],[0,0]],"v":[[26.083,-31.924],[26.385,-42.499],[26.385,-44.312],[45.319,-44.312],[45.319,-31.924]],"c":true},"ix":2},"nm":"用","mn":"ADBE Vector Shape - Group","hd":false},{"ind":2,"ty":"sh","ix":3,"ks":{"a":0,"k":{"i":[[0,0],[0,0],[0,0],[0,0]],"o":[[0,0],[0,0],[0,0],[0,0]],"v":[[45.319,-67.172],[45.319,-55.49],[26.385,-55.49],[26.385,-67.172]],"c":true},"ix":2},"nm":"用","mn":"ADBE Vector Shape - Group","hd":false},{"ind":3,"ty":"sh","ix":4,"ks":{"a":0,"k":{"i":[[0,0],[0,0],[0,0],[0,0]],"o":[[0,0],[0,0],[0,0],[0,0]],"v":[[78.653,-55.49],[57.404,-55.49],[57.404,-67.172],[78.653,-67.172]],"c":true},"ix":2},"nm":"用","mn":"ADBE Vector Shape - Group","hd":false},{"ind":4,"ty":"sh","ix":5,"ks":{"a":0,"k":{"i":[[0,0],[0,0],[0,0],[10.977,-12.085],[-1.913,-2.216],[-1.813,10.977],[0,0],[0,0],[0,0],[0,0],[0,0],[0,0],[1.913,0],[5.64,0.302],[-0.403,-3.223],[-4.129,2.014],[0,6.445]],"o":[[0,0],[0,0],[0,14.099],[2.719,1.41],[7.251,-7.855],[0,0],[0,0],[0,0],[0,0],[0,0],[0,0],[0,1.813],[-1.813,0],[1.511,3.122],[9.064,0.101],[4.028,-1.813],[0,0]],"v":[[90.536,-78.552],[14.502,-78.552],[14.502,-42.599],[2.618,1.511],[12.085,9.265],[24.774,-20.645],[45.319,-20.645],[45.319,7.452],[57.404,7.452],[57.404,-20.645],[78.653,-20.645],[78.653,-5.539],[76.035,-3.122],[61.935,-3.323],[65.762,8.157],[85.098,6.042],[90.536,-5.438]],"c":true},"ix":2},"nm":"用","mn":"ADBE Vector Shape - Group","hd":false}],"nm":"用","np":8,"cix":2,"bm":0,"ix":1,"mn":"ADBE Vector Group","hd":false}]},"fFamily":"Noto Sans JP"},{"ch":"メ","size":16,"style":"Bold","w":89.2,"data":{"shapes":[{"ty":"gr","it":[{"ind":0,"ty":"sh","ix":1,"ks":{"a":0,"k":{"i":[[-1.309,2.316],[0,0],[0.906,-2.618],[5.136,-8.057],[8.057,4.935],[0,0],[-7.251,-5.74],[16.415,-7.956],[0,0],[-8.862,10.675],[-7.05,-8.258],[0,0],[8.862,7.251],[-3.021,7.956]],"o":[[0,0],[-0.403,2.618],[-2.618,7.956],[-8.157,-6.042],[0,0],[10.272,6.244],[-9.97,11.984],[0,0],[17.02,-9.265],[8.057,6.949],[0,0],[-6.848,-7.251],[5.942,-9.265],[1.007,-2.316]],"v":[[79.197,-74.02],[64.191,-79.257],[61.774,-69.992],[50.596,-46.024],[23.807,-64.252],[15.247,-53.979],[42.438,-34.845],[4.169,-5.136],[15.449,5.035],[52.912,-26.083],[75.269,-3.827],[85.642,-15.308],[61.472,-37.564],[74.967,-64.957]],"c":true},"ix":2},"nm":"メ","mn":"ADBE Vector Shape - Group","hd":false}],"nm":"メ","np":3,"cix":2,"bm":0,"ix":1,"mn":"ADBE Vector Group","hd":false}]},"fFamily":"Noto Sans JP"},{"ch":"デ","size":16,"style":"Bold","w":94.2,"data":{"shapes":[{"ty":"gr","it":[{"ind":0,"ty":"sh","ix":1,"ks":{"a":0,"k":{"i":[[3.223,0.504],[0,0],[-3.424,0],[0,0],[-3.424,-0.201],[0,0],[3.424,0],[0,0]],"o":[[0,0],[3.021,-0.201],[0,0],[3.525,0],[0,0],[-3.424,0.504],[0,0],[-3.424,0]],"v":[[16.033,-76.035],[16.033,-63.043],[26.809,-63.345],[59.74,-63.345],[70.617,-63.043],[70.617,-76.035],[59.74,-75.229],[26.809,-75.229]],"c":true},"ix":2},"nm":"デ","mn":"ADBE Vector Shape - Group","hd":false},{"ind":1,"ty":"sh","ix":2,"ks":{"a":0,"k":{"i":[[3.021,0.403],[0,0],[-2.921,0],[0,0],[4.129,-6.244],[7.15,-2.719],[0,0],[-3.525,7.05],[-0.604,10.373],[0,0],[-2.518,-0.201],[0,0],[2.115,0],[0,0]],"o":[[0,0],[2.82,-0.201],[0,0],[-0.403,8.459],[-4.028,5.942],[0,0],[8.963,-4.532],[3.625,-7.05],[0,0],[2.82,0],[0,0],[-2.618,0.403],[0,0],[-3.122,0]],"v":[[4.351,-50.253],[4.351,-37.061],[14.019,-37.463],[41.714,-37.463],[35.47,-15.207],[17.242,-0.806],[29.024,7.755],[49.267,-11.581],[55.712,-37.463],[79.983,-37.463],[89.147,-37.161],[89.147,-50.253],[79.983,-49.649],[14.019,-49.649]],"c":true},"ix":2},"nm":"デ","mn":"ADBE Vector Shape - Group","hd":false},{"ind":2,"ty":"sh","ix":3,"ks":{"a":0,"k":{"i":[[2.518,3.726],[0,0],[-2.115,-4.129],[0,0]],"o":[[0,0],[2.719,3.827],[0,0],[-1.913,-3.726]],"v":[[76.659,-82.983],[68.603,-79.66],[76.559,-65.662],[84.615,-69.186]],"c":true},"ix":2},"nm":"デ","mn":"ADBE Vector Shape - Group","hd":false},{"ind":3,"ty":"sh","ix":4,"ks":{"a":0,"k":{"i":[[2.618,3.827],[0,0],[-2.115,-4.23],[0,0]],"o":[[0,0],[2.719,3.827],[0,0],[-1.813,-3.525]],"v":[[88.543,-87.515],[80.587,-84.192],[88.644,-70.294],[96.7,-73.819]],"c":true},"ix":2},"nm":"デ","mn":"ADBE Vector Shape - Group","hd":false}],"nm":"デ","np":7,"cix":2,"bm":0,"ix":1,"mn":"ADBE Vector Group","hd":false}]},"fFamily":"Noto Sans JP"},{"ch":"ィ","size":16,"style":"Bold","w":80.6,"data":{"shapes":[{"ty":"gr","it":[{"ind":0,"ty":"sh","ix":1,"ks":{"a":0,"k":{"i":[[13.092,-2.82],[0,0],[-8.862,4.431],[0,0],[0.201,-2.014],[0,0],[0,3.525],[0,0],[-4.733,5.237],[0,0],[9.769,-5.942]],"o":[[0,0],[8.762,-2.719],[0,0],[0,3.525],[0,0],[-0.604,-2.014],[0,0],[8.963,-5.942],[0,0],[-5.136,6.546],[-7.956,4.834]],"v":[[5.376,-28.702],[11.318,-16.818],[40.221,-28.601],[40.221,-2.014],[39.717,8.862],[54.622,8.862],[53.917,-2.014],[53.917,-36.557],[76.476,-54.886],[66.506,-64.655],[41.429,-43.103]],"c":true},"ix":2},"nm":"ィ","mn":"ADBE Vector Shape - Group","hd":false}],"nm":"ィ","np":3,"cix":2,"bm":0,"ix":1,"mn":"ADBE Vector Group","hd":false}]},"fFamily":"Noto Sans JP"},{"ch":"ア","size":16,"style":"Bold","w":93.1,"data":{"shapes":[{"ty":"gr","it":[{"ind":0,"ty":"sh","ix":1,"ks":{"a":0,"k":{"i":[[-1.108,1.309],[0,0],[2.82,0],[0,0],[3.827,0.604],[0,0],[-4.23,0],[0,0],[8.057,-4.935],[0,0],[-4.733,7.855]],"o":[[0,0],[-1.913,0.604],[0,0],[-4.23,0],[0,0],[4.733,-0.403],[0,0],[-2.618,4.935],[0,0],[9.869,-7.05],[0.906,-1.511]],"v":[[92.576,-68.179],[84.62,-75.632],[74.348,-74.725],[20.066,-74.725],[7.78,-75.732],[7.78,-61.734],[20.066,-62.439],[72.535,-62.439],[54.005,-43.707],[64.479,-35.349],[88.649,-62.943]],"c":true},"ix":2},"nm":"ア","mn":"ADBE Vector Shape - Group","hd":false},{"ind":1,"ty":"sh","ix":2,"ks":{"a":0,"k":{"i":[[0,24.976],[0,0],[0,-3.122],[12.79,-8.862],[3.223,-1.108],[0,0]],"o":[[0,0],[0.504,3.223],[0,16.516],[-3.726,2.719],[0,0],[27.393,-14.703]],"v":[[51.487,-54.584],[36.885,-54.584],[37.59,-45.52],[22.383,-9.467],[11.808,-3.928],[23.591,5.64]],"c":true},"ix":2},"nm":"ア","mn":"ADBE Vector Shape - Group","hd":false}],"nm":"ア","np":5,"cix":2,"bm":0,"ix":1,"mn":"ADBE Vector Group","hd":false}]},"fFamily":"Noto Sans JP"},{"ch":"掲","size":16,"style":"Bold","w":100,"data":{"shapes":[{"ty":"gr","it":[{"ind":0,"ty":"sh","ix":1,"ks":{"a":0,"k":{"i":[[0,0],[0,0],[0,0],[0,0],[0,0],[0,0],[0,0],[0,0],[0,0],[0,0],[0,0],[0,0],[0,0],[3.827,-0.806],[0,0],[0,0],[0,0],[1.208,0],[3.928,0.201],[-0.302,-3.223],[-3.323,2.014],[0,5.942],[0,0],[-2.921,0.906]],"o":[[0,0],[0,0],[0,0],[0,0],[0,0],[0,0],[0,0],[0,0],[0,0],[0,0],[0,0],[0,0],[-5.136,1.208],[0,0],[0,0],[0,0],[0,1.511],[-1.309,0.101],[1.511,3.323],[6.949,0],[3.223,-1.813],[0,0],[3.021,-0.906],[0,0]],"v":[[35.248,-41.995],[27.594,-39.981],[27.594,-55.289],[35.953,-55.289],[35.953,-66.266],[27.594,-66.266],[27.594,-85.199],[16.113,-85.199],[16.113,-66.266],[4.431,-66.266],[4.431,-55.289],[16.113,-55.289],[16.113,-37.161],[2.417,-34.039],[4.935,-22.458],[16.113,-25.479],[16.113,-4.834],[14.401,-2.921],[5.035,-3.021],[8.359,8.661],[23.364,6.244],[27.594,-4.733],[27.594,-28.702],[36.557,-31.32]],"c":true},"ix":2},"nm":"掲","mn":"ADBE Vector Shape - Group","hd":false},{"ind":1,"ty":"sh","ix":2,"ks":{"a":0,"k":{"i":[[0,0],[0,2.518],[0,0],[-6.244,2.618],[0,0],[5.438,-1.511],[0,0],[0,0],[-0.604,0.806],[0,0],[2.014,-2.014],[1.712,0],[1.813,0.101],[-0.806,6.143],[2.014,1.41],[2.316,0]],"o":[[-2.921,0],[0,0],[7.05,-1.41],[0,0],[-3.525,1.813],[0,0],[0,0],[0.604,-0.806],[0,0],[-1.108,18.832],[-1.007,1.007],[-0.906,0],[3.323,-1.309],[-2.719,-0.604],[-0.302,4.935],[0,0]],"v":[[55.893,-9.366],[52.469,-12.286],[52.469,-14.905],[73.819,-21.048],[66.87,-28.4],[52.469,-23.264],[52.469,-28.702],[49.85,-28.702],[51.562,-31.018],[83.89,-31.018],[79.358,-2.216],[75.732,-0.906],[71.503,-1.007],[77.142,-11.481],[68.179,-15.106],[65.057,-9.366]],"c":true},"ix":2},"nm":"掲","mn":"ADBE Vector Shape - Group","hd":false},{"ind":2,"ty":"sh","ix":3,"ks":{"a":0,"k":{"i":[[0,0],[0,0],[0,0],[0,0]],"o":[[0,0],[0,0],[0,0],[0,0]],"v":[[52.167,-60.526],[79.559,-60.526],[79.559,-55.087],[52.167,-55.087]],"c":true},"ix":2},"nm":"掲","mn":"ADBE Vector Shape - Group","hd":false},{"ind":3,"ty":"sh","ix":4,"ks":{"a":0,"k":{"i":[[0,0],[0,0],[0,0],[0,0]],"o":[[0,0],[0,0],[0,0],[0,0]],"v":[[52.167,-73.718],[79.559,-73.718],[79.559,-68.381],[52.167,-68.381]],"c":true},"ix":2},"nm":"掲","mn":"ADBE Vector Shape - Group","hd":false},{"ind":4,"ty":"sh","ix":5,"ks":{"a":0,"k":{"i":[[0,0],[-0.705,1.913],[0,0],[0,0],[0,0],[0,0],[0,0],[7.452,-5.035],[-1.712,-2.115],[-1.309,1.208],[0,0],[-10.071,0],[0,0],[-0.201,-2.518],[-3.021,0.302],[-2.216,2.719],[-1.41,26.688],[0,0]],"o":[[1.007,-1.913],[0,0],[0,0],[0,0],[0,0],[0,0],[-4.028,8.661],[2.518,1.813],[1.309,-1.007],[0,0],[0,9.164],[0,0],[1.309,2.719],[5.035,0.201],[3.223,-0.504],[3.223,-3.726],[0.201,-1.41],[0,0]],"v":[[57.504,-40.887],[60.123,-46.628],[90.939,-46.628],[90.939,-82.178],[41.29,-82.178],[41.29,-46.628],[47.836,-46.628],[30.011,-25.076],[38.37,-16.919],[42.297,-20.343],[42.297,-12.186],[54.584,-0.201],[65.863,-0.201],[68.28,8.56],[81.07,8.459],[89.026,4.431],[95.27,-36.255],[95.572,-40.887]],"c":true},"ix":2},"nm":"掲","mn":"ADBE Vector Shape - Group","hd":false}],"nm":"掲","np":8,"cix":2,"bm":0,"ix":1,"mn":"ADBE Vector Group","hd":false}]},"fFamily":"Noto Sans JP"},{"ch":"載","size":16,"style":"Bold","w":100,"data":{"shapes":[{"ty":"gr","it":[{"ind":0,"ty":"sh","ix":1,"ks":{"a":0,"k":{"i":[[0,0],[4.431,4.028],[0,0],[-2.216,-3.928]],"o":[[-2.618,-4.028],[0,0],[4.33,4.23],[0,0]],"v":[[94.666,-71.1],[81.976,-84.897],[73.215,-79.056],[85.3,-64.655]],"c":true},"ix":2},"nm":"載","mn":"ADBE Vector Shape - Group","hd":false},{"ind":1,"ty":"sh","ix":2,"ks":{"a":0,"k":{"i":[[0,0],[0,0],[0,0],[0,0],[0,0],[0,0],[0,0],[0,0],[0,0],[0,0],[0,0],[0,0],[-2.82,-10.574],[3.223,-2.618]],"o":[[0,0],[0,0],[0,0],[0,0],[0,0],[0,0],[0,0],[0,0],[0,0],[0,0],[0,0],[0.806,14.703],[-2.82,3.323],[0,0]],"v":[[54.886,-8.762],[36.456,-8.762],[36.456,-12.689],[53.577,-12.689],[53.577,-37.463],[36.557,-37.463],[36.557,-41.391],[54.987,-41.391],[54.987,-49.75],[36.557,-49.75],[36.557,-54.181],[58.713,-54.181],[64.05,-15.408],[54.886,-6.546]],"c":true},"ix":2},"nm":"載","mn":"ADBE Vector Shape - Group","hd":false},{"ind":2,"ty":"sh","ix":3,"ks":{"a":0,"k":{"i":[[0,0],[0,0],[0,0],[0,0]],"o":[[0,0],[0,0],[0,0],[0,0]],"v":[[17.825,-22.256],[26.889,-22.256],[26.889,-18.53],[17.825,-18.53]],"c":true},"ix":2},"nm":"載","mn":"ADBE Vector Shape - Group","hd":false},{"ind":3,"ty":"sh","ix":4,"ks":{"a":0,"k":{"i":[[0,0],[0,0],[0,0],[0,0]],"o":[[0,0],[0,0],[0,0],[0,0]],"v":[[17.825,-31.622],[26.889,-31.622],[26.889,-27.896],[17.825,-27.896]],"c":true},"ix":2},"nm":"載","mn":"ADBE Vector Shape - Group","hd":false},{"ind":4,"ty":"sh","ix":5,"ks":{"a":0,"k":{"i":[[0,0],[0,0],[0,0],[0,0]],"o":[[0,0],[0,0],[0,0],[0,0]],"v":[[35.55,-27.896],[35.55,-31.622],[44.815,-31.622],[44.815,-27.896]],"c":true},"ix":2},"nm":"載","mn":"ADBE Vector Shape - Group","hd":false},{"ind":5,"ty":"sh","ix":6,"ks":{"a":0,"k":{"i":[[0,0],[0,0],[0,0],[0,0]],"o":[[0,0],[0,0],[0,0],[0,0]],"v":[[35.55,-18.53],[35.55,-22.256],[44.815,-22.256],[44.815,-18.53]],"c":true},"ix":2},"nm":"載","mn":"ADBE Vector Shape - Group","hd":false},{"ind":6,"ty":"sh","ix":7,"ks":{"a":0,"k":{"i":[[0,0],[3.726,-6.445],[0.604,9.567],[0,0],[0,0],[0,0],[-0.201,7.251],[0,0],[-0.302,-6.949],[0,0],[0,0],[0,0],[0,0],[0,0],[0,0],[0,0],[0,0],[0,0],[0,0],[0,0],[0,0],[0,0],[0,0],[0,0],[0,0],[0,0],[0,0],[0,0],[0,0],[0,0],[0,0],[0,0],[0,0],[0,0],[0,0],[0,0],[0,0],[0,0],[0,0],[0,0],[-1.712,-3.021],[-4.431,4.532],[-6.445,0],[-1.611,17.523],[2.518,2.719],[2.014,0],[2.216,6.546],[-4.028,12.589]],"o":[[-2.316,7.755],[-1.309,-7.452],[0,0],[0,0],[0,0],[-0.201,-6.848],[0,0],[0,7.15],[0,0],[0,0],[0,0],[0,0],[0,0],[0,0],[0,0],[0,0],[0,0],[0,0],[0,0],[0,0],[0,0],[0,0],[0,0],[0,0],[0,0],[0,0],[0,0],[0,0],[0,0],[0,0],[0,0],[0,0],[0,0],[0,0],[0,0],[0,0],[0,0],[0,0],[0,0],[2.921,2.417],[5.338,-3.525],[3.726,7.553],[8.862,0],[-2.921,-1.108],[-0.504,11.682],[-3.021,0],[6.848,-9.467],[0,0]],"v":[[82.379,-49.85],[73.215,-28.4],[70.395,-54.181],[96.075,-54.181],[96.075,-64.05],[69.992,-64.05],[69.891,-85.199],[57.806,-85.199],[58.209,-64.05],[37.061,-64.05],[37.061,-69.388],[53.174,-69.388],[53.174,-78.452],[37.061,-78.452],[37.061,-85.199],[25.58,-85.199],[25.58,-78.452],[9.366,-78.452],[9.366,-69.388],[25.58,-69.388],[25.58,-64.05],[4.935,-64.05],[4.935,-54.181],[25.781,-54.181],[25.781,-49.75],[7.654,-49.75],[7.654,-41.391],[25.781,-41.391],[25.781,-37.463],[9.467,-37.463],[9.467,-12.689],[25.983,-12.689],[25.983,-8.762],[6.244,-8.762],[6.244,-0.101],[25.983,-0.101],[25.983,8.862],[36.456,8.862],[36.456,-0.101],[45.822,-0.101],[53.778,8.963],[68.381,-3.223],[83.487,8.762],[97.586,-13.092],[88.12,-19.437],[84.595,-2.921],[76.74,-13.293],[93.054,-46.527]],"c":true},"ix":2},"nm":"載","mn":"ADBE Vector Shape - Group","hd":false}],"nm":"載","np":10,"cix":2,"bm":0,"ix":1,"mn":"ADBE Vector Group","hd":false}]},"fFamily":"Noto Sans JP"},{"ch":"料","size":16,"style":"Bold","w":100,"data":{"shapes":[{"ty":"gr","it":[{"ind":0,"ty":"sh","ix":1,"ks":{"a":0,"k":{"i":[[0,0],[5.64,3.323],[0,0],[-3.122,-3.928]],"o":[[-3.223,-3.726],[0,0],[5.539,3.726],[0,0]],"v":[[72.409,-67.676],[56.396,-79.861],[50.656,-71.805],[66.266,-58.713]],"c":true},"ix":2},"nm":"料","mn":"ADBE Vector Shape - Group","hd":false},{"ind":1,"ty":"sh","ix":2,"ks":{"a":0,"k":{"i":[[0,0],[-3.323,-3.726],[0,0],[5.841,3.122]],"o":[[5.841,3.525],[0,0],[-3.625,-3.625],[0,0]],"v":[[46.024,-46.527],[62.54,-33.939],[68.582,-43.506],[51.663,-55.087]],"c":true},"ix":2},"nm":"料","mn":"ADBE Vector Shape - Group","hd":false},{"ind":2,"ty":"sh","ix":3,"ks":{"a":0,"k":{"i":[[0,0],[2.014,-6.345],[0,0],[-2.618,8.057]],"o":[[-1.108,7.05],[0,0],[2.518,-5.841],[0,0]],"v":[[36.96,-79.761],[31.421,-56.195],[38.974,-54.08],[47.031,-77.545]],"c":true},"ix":2},"nm":"料","mn":"ADBE Vector Shape - Group","hd":false},{"ind":3,"ty":"sh","ix":4,"ks":{"a":0,"k":{"i":[[0,0],[2.618,7.251],[0,0],[-0.201,-6.244]],"o":[[-0.504,-6.244],[0,0],[2.316,7.251],[0,0]],"v":[[17.422,-56.195],[12.286,-79.257],[3.928,-77.042],[8.459,-53.778]],"c":true},"ix":2},"nm":"料","mn":"ADBE Vector Shape - Group","hd":false},{"ind":4,"ty":"sh","ix":5,"ks":{"a":0,"k":{"i":[[0,0],[2.921,2.921],[0,0],[0,0],[0,0],[0,0],[0,0],[0,0],[0,0],[0,0],[0,0],[0,0],[5.035,-6.143],[-1.007,-3.625],[-3.223,9.366],[0,0],[0,0],[0,0],[-1.511,-3.223]],"o":[[-2.115,-2.82],[0,0],[0,0],[0,0],[0,0],[0,0],[0,0],[0,0],[0,0],[0,0],[0,0],[-3.122,9.164],[1.813,3.323],[4.33,-6.042],[0,0],[0,0],[0,0],[2.921,4.633],[0,0]],"v":[[44.916,-23.062],[30.313,-40.082],[30.313,-40.787],[45.218,-40.787],[45.218,-51.965],[30.313,-51.965],[30.313,-84.897],[19.235,-84.897],[19.235,-51.965],[4.028,-51.965],[4.028,-40.787],[15.509,-40.787],[2.216,-14.703],[7.654,-2.316],[19.235,-27.09],[19.235,8.459],[30.313,8.459],[30.313,-26.889],[37.564,-13.797]],"c":true},"ix":2},"nm":"料","mn":"ADBE Vector Shape - Group","hd":false},{"ind":5,"ty":"sh","ix":6,"ks":{"a":0,"k":{"i":[[0,0],[0,0],[0,0],[0,0],[0,0],[0,0],[0,0],[0,0],[0,0],[0,0],[0,0],[0,0]],"o":[[0,0],[0,0],[0,0],[0,0],[0,0],[0,0],[0,0],[0,0],[0,0],[0,0],[0,0],[0,0]],"v":[[98.19,-20.746],[96.378,-31.924],[86.105,-30.011],[86.105,-85.4],[74.826,-85.4],[74.826,-27.997],[44.916,-22.659],[46.729,-11.481],[74.826,-16.516],[74.826,8.661],[86.105,8.661],[86.105,-18.53]],"c":true},"ix":2},"nm":"料","mn":"ADBE Vector Shape - Group","hd":false}],"nm":"料","np":9,"cix":2,"bm":0,"ix":1,"mn":"ADBE Vector Group","hd":false}]},"fFamily":"Noto Sans JP"},{"ch":"広","size":16,"style":"Bold","w":100,"data":{"shapes":[{"ty":"gr","it":[{"ind":0,"ty":"sh","ix":1,"ks":{"a":0,"k":{"i":[[0,0],[0,0],[0,0],[0,0],[0,0],[0,0],[0,0],[0,0],[0,0],[8.661,-14.2],[-2.216,-2.014],[0,15.912]],"o":[[0,0],[0,0],[0,0],[0,0],[0,0],[0,0],[0,0],[0,0],[0,14.2],[2.82,1.108],[9.467,-15.207],[0,0]],"v":[[23.767,-61.029],[96.075,-61.029],[96.075,-72.51],[59.72,-72.51],[59.72,-85.199],[47.232,-85.199],[47.232,-72.51],[11.783,-72.51],[11.783,-47.131],[2.417,1.913],[12.689,8.56],[23.767,-47.131]],"c":true},"ix":2},"nm":"広","mn":"ADBE Vector Shape - Group","hd":false},{"ind":1,"ty":"sh","ix":2,"ks":{"a":0,"k":{"i":[[0,0],[8.661,11.481],[0,0],[-3.525,-6.445],[9.567,-0.403],[-3.928,15.207],[0,0],[5.035,-13.495],[3.525,-0.101],[0,0],[-21.249,1.712],[-0.806,-2.618]],"o":[[-3.625,-10.574],[0,0],[4.028,5.64],[-10.373,0.604],[4.834,-12.689],[0,0],[-2.719,15.207],[-4.33,0.101],[0,0],[15.61,-0.906],[1.511,3.122],[0,0]],"v":[[98.291,3.424],[76.538,-33.838],[65.359,-29.004],[77.142,-10.373],[46.628,-8.862],[60.626,-53.577],[46.93,-56.296],[33.737,-8.258],[21.954,-7.855],[23.062,4.532],[82.48,0.302],[85.904,8.963]],"c":true},"ix":2},"nm":"広","mn":"ADBE Vector Shape - Group","hd":false}],"nm":"広","np":5,"cix":2,"bm":0,"ix":1,"mn":"ADBE Vector Group","hd":false}]},"fFamily":"Noto Sans JP"},{"ch":"告","size":16,"style":"Bold","w":100,"data":{"shapes":[{"ty":"gr","it":[{"ind":0,"ty":"sh","ix":1,"ks":{"a":0,"k":{"i":[[0,0],[0,0],[0,0],[0,0]],"o":[[0,0],[0,0],[0,0],[0,0]],"v":[[72.208,-20.444],[72.208,-6.848],[29.91,-6.848],[29.91,-20.444]],"c":true},"ix":2},"nm":"告","mn":"ADBE Vector Shape - Group","hd":false},{"ind":1,"ty":"sh","ix":2,"ks":{"a":0,"k":{"i":[[0,0],[0,0],[0,0],[0,0],[0,0],[0,0],[0,0],[0,0]],"o":[[0,0],[0,0],[0,0],[0,0],[0,0],[0,0],[0,0],[0,0]],"v":[[17.624,9.164],[29.91,9.164],[29.91,4.23],[72.208,4.23],[72.208,8.862],[85.098,8.862],[85.098,-31.522],[17.624,-31.522]],"c":true},"ix":2},"nm":"告","mn":"ADBE Vector Shape - Group","hd":false},{"ind":2,"ty":"sh","ix":3,"ks":{"a":0,"k":{"i":[[0,0],[0,0],[0,0],[0,0],[0,0],[0,0],[0,0],[0,0],[0,0],[-1.108,3.323],[0,0],[7.251,-6.848],[-2.518,-1.913],[-2.618,4.431],[0,0],[0,0],[0,0],[0,0],[0,0],[0,0]],"o":[[0,0],[0,0],[0,0],[0,0],[0,0],[0,0],[0,0],[0,0],[1.511,-3.223],[0,0],[-3.525,10.876],[3.021,1.309],[2.82,-3.122],[0,0],[0,0],[0,0],[0,0],[0,0],[0,0],[0,0]],"v":[[59.216,-49.75],[59.216,-61.331],[88.623,-61.331],[88.623,-72.308],[59.216,-72.308],[59.216,-85.4],[46.527,-85.4],[46.527,-72.308],[30.515,-72.308],[34.442,-82.077],[22.458,-85.098],[5.338,-56.296],[16.315,-49.951],[24.573,-61.331],[46.527,-61.331],[46.527,-49.75],[6.042,-49.75],[6.042,-38.672],[94.766,-38.672],[94.766,-49.75]],"c":true},"ix":2},"nm":"告","mn":"ADBE Vector Shape - Group","hd":false}],"nm":"告","np":6,"cix":2,"bm":0,"ix":1,"mn":"ADBE Vector Group","hd":false}]},"fFamily":"Noto Sans JP"},{"ch":"・","size":16,"style":"Bold","w":50,"data":{"shapes":[{"ty":"gr","it":[{"ind":0,"ty":"sh","ix":1,"ks":{"a":0,"k":{"i":[[7.05,0],[0,-7.05],[-7.05,0],[0,7.05]],"o":[[-7.05,0],[0,7.05],[7.05,0],[0,-7.05]],"v":[[25.354,-51.16],[12.463,-38.269],[25.354,-25.378],[38.245,-38.269]],"c":true},"ix":2},"nm":"・","mn":"ADBE Vector Shape - Group","hd":false}],"nm":"・","np":3,"cix":2,"bm":0,"ix":1,"mn":"ADBE Vector Group","hd":false}]},"fFamily":"Noto Sans JP"}]}